[
    {
        "type": "click",
        "e": "click",
        "timestamp": "2024-10-18T02:52:04.031Z",
        "target": "BUTTON",
        "x": 738,
        "y": 19,
        "timestamp_second": 0.0,
        "relative_time": 0.0,
        "index": 0
    },
    {
        "type": "mouseMovement",
        "totalMouseMovement": 192.50938564844773,
        "timestamp": "2024-10-18T02:52:04.039Z",
        "duration": 0.106,
        "timestamp_second": 0.008,
        "relative_time": 0.00014814814814814815,
        "index": 1
    },
    {
        "type": "idle",
        "timestamp": "2024-10-18T02:52:07.158Z",
        "duration": 3.053,
        "timestamp_second": 3.127,
        "relative_time": 0.05790740740740741,
        "index": 2
    },
    {
        "type": "mouseMovement",
        "totalMouseMovement": 342.0386648448721,
        "timestamp": "2024-10-18T02:52:07.198Z",
        "duration": 0.347,
        "timestamp_second": 3.167,
        "relative_time": 0.058648148148148144,
        "index": 3
    },
    {
        "type": "mousewheel",
        "timestamp": "2024-10-18T02:52:07.867Z",
        "deltaY": 964,
        "yDirection": 1,
        "duration": 2.258,
        "timestamp_second": 3.836,
        "relative_time": 0.07103703703703704,
        "index": 4
    },
    {
        "type": "scroll",
        "timestamp": "2024-10-18T02:52:10.627Z",
        "deltaY": 1,
        "yDirection": 1,
        "timestamp_second": 6.596,
        "relative_time": 0.12214814814814816,
        "index": 5
    },
    {
        "type": "mouseMovement",
        "totalMouseMovement": 316.1892433740077,
        "timestamp": "2024-10-18T02:52:10.644Z",
        "duration": 0.066,
        "timestamp_second": 6.613,
        "relative_time": 0.12246296296296298,
        "index": 6
    },
    {
        "type": "idle",
        "timestamp": "2024-10-18T02:52:13.711Z",
        "duration": 17.083000000000002,
        "timestamp_second": 9.68,
        "relative_time": 0.17925925925925926,
        "index": 7
    },
    {
        "type": "mouseMovement",
        "totalMouseMovement": 785.7719031566153,
        "timestamp": "2024-10-18T02:52:27.793Z",
        "duration": 2.798,
        "timestamp_second": 23.762,
        "relative_time": 0.44003703703703706,
        "index": 8
    },
    {
        "type": "click",
        "e": "click",
        "timestamp": "2024-10-18T02:52:30.676Z",
        "target": "P",
        "x": 368,
        "y": 135,
        "timestamp_second": 26.645,
        "relative_time": 0.4934259259259259,
        "index": 9
    },
    {
        "type": "mouseMovement",
        "totalMouseMovement": 46.03329637837305,
        "timestamp": "2024-10-18T02:52:31.057Z",
        "duration": 0.151,
        "timestamp_second": 27.026,
        "relative_time": 0.5004814814814814,
        "index": 10
    },
    {
        "type": "click",
        "e": "click",
        "timestamp": "2024-10-18T02:52:31.210Z",
        "target": "P",
        "x": 306,
        "y": 138,
        "timestamp_second": 27.179,
        "relative_time": 0.5033148148148148,
        "index": 11
    },
    {
        "type": "mouseMovement",
        "totalMouseMovement": 444.15745026192235,
        "timestamp": "2024-10-18T02:52:31.462Z",
        "duration": 0.073,
        "timestamp_second": 27.431,
        "relative_time": 0.5079814814814815,
        "index": 12
    },
    {
        "type": "idle",
        "timestamp": "2024-10-18T02:52:34.543Z",
        "duration": 14.361999999999998,
        "timestamp_second": 30.512,
        "relative_time": 0.5650370370370371,
        "index": 13
    },
    {
        "type": "mouseMovement",
        "totalMouseMovement": 238.6756808188493,
        "timestamp": "2024-10-18T02:52:45.897Z",
        "duration": 0.414,
        "timestamp_second": 41.866,
        "relative_time": 0.7752962962962964,
        "index": 14
    },
    {
        "type": "mousewheel",
        "timestamp": "2024-10-18T02:52:46.878Z",
        "deltaY": 123,
        "yDirection": 1,
        "duration": 0.409,
        "timestamp_second": 42.847,
        "relative_time": 0.793462962962963,
        "index": 15
    },
    {
        "type": "scroll",
        "timestamp": "2024-10-18T02:52:47.798Z",
        "deltaY": 0,
        "yDirection": 0,
        "timestamp_second": 43.767,
        "relative_time": 0.8105000000000001,
        "index": 16
    },
    {
        "type": "mouseMovement",
        "totalMouseMovement": 562.9585594659811,
        "timestamp": "2024-10-18T02:52:47.806Z",
        "duration": 0.736,
        "timestamp_second": 43.775,
        "relative_time": 0.8106481481481482,
        "index": 17
    },
    {
        "type": "mousewheel",
        "timestamp": "2024-10-18T02:52:49.298Z",
        "deltaY": 87,
        "yDirection": 2,
        "duration": 0.31,
        "timestamp_second": 45.267,
        "relative_time": 0.8382777777777779,
        "index": 18
    },
    {
        "type": "scroll",
        "timestamp": "2024-10-18T02:52:50.119Z",
        "deltaY": 0,
        "yDirection": 0,
        "timestamp_second": 46.088,
        "relative_time": 0.8534814814814815,
        "index": 19
    },
    {
        "type": "mouseMovement",
        "totalMouseMovement": 67.7038568301341,
        "timestamp": "2024-10-18T02:52:50.142Z",
        "duration": 0.449,
        "timestamp_second": 46.111,
        "relative_time": 0.8539074074074073,
        "index": 20
    },
    {
        "type": "click",
        "e": "click",
        "timestamp": "2024-10-18T02:52:50.593Z",
        "target": "P",
        "x": 527,
        "y": 200,
        "timestamp_second": 46.562,
        "relative_time": 0.8622592592592592,
        "index": 21
    },
    {
        "type": "mouseMovement",
        "totalMouseMovement": 352.3580699795939,
        "timestamp": "2024-10-18T02:52:51.583Z",
        "duration": 0.14,
        "timestamp_second": 47.552,
        "relative_time": 0.8805925925925926,
        "index": 22
    },
    {
        "type": "idle",
        "timestamp": "2024-10-18T02:52:54.723Z",
        "duration": 117.914,
        "timestamp_second": 50.692,
        "relative_time": 0.9387407407407407,
        "index": 23
    },
    {
        "type": "mouseMovement",
        "totalMouseMovement": 271.09993450901857,
        "timestamp": "2024-10-18T02:54:49.637Z",
        "duration": 0.349,
        "timestamp_second": 165.606,
        "relative_time": 3.066777777777778,
        "index": 24
    },
    {
        "type": "mousewheel",
        "timestamp": "2024-10-18T02:54:50.455Z",
        "deltaY": 886,
        "yDirection": 1,
        "duration": 2.328,
        "timestamp_second": 166.424,
        "relative_time": 3.081925925925926,
        "index": 25
    },
    {
        "type": "scroll",
        "timestamp": "2024-10-18T02:54:53.288Z",
        "deltaY": 0,
        "yDirection": 0,
        "timestamp_second": 169.257,
        "relative_time": 3.1343888888888887,
        "index": 26
    },
    {
        "type": "mousewheel",
        "timestamp": "2024-10-18T02:54:53.818Z",
        "deltaY": 839,
        "yDirection": 2,
        "duration": 1.48,
        "timestamp_second": 169.787,
        "relative_time": 3.144203703703704,
        "index": 27
    },
    {
        "type": "mousewheel",
        "timestamp": "2024-10-18T02:54:55.348Z",
        "deltaY": 0,
        "yDirection": 0,
        "duration": 0.068,
        "timestamp_second": 171.317,
        "relative_time": 3.1725370370370367,
        "index": 28
    },
    {
        "type": "mousewheel",
        "timestamp": "2024-10-18T02:54:55.447Z",
        "deltaY": 119,
        "yDirection": 2,
        "duration": 0.301,
        "timestamp_second": 171.416,
        "relative_time": 3.1743703703703705,
        "index": 29
    },
    {
        "type": "scroll",
        "timestamp": "2024-10-18T02:54:56.262Z",
        "deltaY": 1,
        "yDirection": 2,
        "timestamp_second": 172.231,
        "relative_time": 3.1894629629629625,
        "index": 30
    },
    {
        "type": "mouseMovement",
        "totalMouseMovement": 182.98203485876456,
        "timestamp": "2024-10-18T02:54:56.531Z",
        "duration": 0.027,
        "timestamp_second": 172.5,
        "relative_time": 3.194444444444444,
        "index": 31
    },
    {
        "type": "idle",
        "timestamp": "2024-10-18T02:54:59.561Z",
        "duration": 109.828,
        "timestamp_second": 175.53,
        "relative_time": 3.2505555555555556,
        "index": 32
    },
    {
        "type": "mouseMovement",
        "totalMouseMovement": 1579.8234496842688,
        "timestamp": "2024-10-18T02:56:46.386Z",
        "duration": 2.21,
        "timestamp_second": 282.355,
        "relative_time": 5.228796296296297,
        "index": 33
    },
    {
        "type": "click",
        "e": "click",
        "timestamp": "2024-10-18T02:56:48.598Z",
        "target": "HTML",
        "x": 843,
        "y": 500,
        "timestamp_second": 284.567,
        "relative_time": 5.269759259259259,
        "index": 34
    },
    {
        "type": "idle",
        "timestamp": "2024-10-18T02:56:51.597Z",
        "duration": 145.768,
        "timestamp_second": 287.566,
        "relative_time": 5.325296296296296,
        "index": 35
    },
    {
        "type": "mouseMovement",
        "totalMouseMovement": 323.42043095870577,
        "timestamp": "2024-10-18T02:59:14.364Z",
        "duration": 0.258,
        "timestamp_second": 430.333,
        "relative_time": 7.96912962962963,
        "index": 36
    },
    {
        "type": "mousewheel",
        "timestamp": "2024-10-18T02:59:14.976Z",
        "deltaY": 624,
        "yDirection": 1,
        "duration": 0.728,
        "timestamp_second": 430.945,
        "relative_time": 7.980462962962963,
        "index": 37
    },
    {
        "type": "mousewheel",
        "timestamp": "2024-10-18T02:59:15.838Z",
        "deltaY": 38,
        "yDirection": 2,
        "duration": 0.537,
        "timestamp_second": 431.807,
        "relative_time": 7.9964259259259265,
        "index": 38
    },
    {
        "type": "mousewheel",
        "timestamp": "2024-10-18T02:59:16.854Z",
        "deltaY": 455,
        "yDirection": 1,
        "duration": 1.318,
        "timestamp_second": 432.823,
        "relative_time": 8.01524074074074,
        "index": 39
    },
    {
        "type": "mouseMovement",
        "totalMouseMovement": 232.1907816179173,
        "timestamp": "2024-10-18T02:59:18.386Z",
        "duration": 0.282,
        "timestamp_second": 434.355,
        "relative_time": 8.043611111111112,
        "index": 40
    },
    {
        "type": "scroll",
        "timestamp": "2024-10-18T02:59:18.674Z",
        "deltaY": 0,
        "yDirection": 0,
        "timestamp_second": 434.643,
        "relative_time": 8.048944444444443,
        "index": 41
    },
    {
        "type": "mouseMovement",
        "totalMouseMovement": 3.414213562373334,
        "timestamp": "2024-10-18T02:59:18.685Z",
        "duration": 0.083,
        "timestamp_second": 434.654,
        "relative_time": 8.049148148148149,
        "index": 42
    },
    {
        "type": "click",
        "e": "click",
        "timestamp": "2024-10-18T02:59:19.158Z",
        "target": "TEXTAREA",
        "x": 289,
        "y": 233,
        "timestamp_second": 435.127,
        "relative_time": 8.057907407407408,
        "index": 43
    },
    {
        "type": "paste",
        "timestamp": "2024-10-18T02:59:19.484Z",
        "text": "Frederiks Kirke",
        "textLength": 15,
        "timestamp_second": 435.453,
        "relative_time": 8.063944444444445,
        "index": 44
    },
    {
        "type": "mouseMovement",
        "totalMouseMovement": 471.5709203606366,
        "timestamp": "2024-10-18T02:59:19.966Z",
        "duration": 0.363,
        "timestamp_second": 435.935,
        "relative_time": 8.07287037037037,
        "index": 45
    },
    {
        "type": "idle",
        "timestamp": "2024-10-18T02:59:23.337Z",
        "duration": 3.168,
        "timestamp_second": 439.306,
        "relative_time": 8.135296296296296,
        "index": 46
    },
    {
        "type": "mouseMovement",
        "totalMouseMovement": 337.20444027931444,
        "timestamp": "2024-10-18T02:59:23.497Z",
        "duration": 0.283,
        "timestamp_second": 439.466,
        "relative_time": 8.138259259259259,
        "index": 47
    },
    {
        "type": "click",
        "e": "click",
        "timestamp": "2024-10-18T02:59:24.359Z",
        "target": "TEXTAREA",
        "x": 352,
        "y": 259,
        "timestamp_second": 440.328,
        "relative_time": 8.154222222222222,
        "index": 48
    },
    {
        "type": "paste",
        "timestamp": "2024-10-18T02:59:24.862Z",
        "text": "Famous modern architecture",
        "textLength": 26,
        "timestamp_second": 440.831,
        "relative_time": 8.163537037037036,
        "index": 49
    },
    {
        "type": "mouseMovement",
        "totalMouseMovement": 521.3077235823384,
        "timestamp": "2024-10-18T02:59:25.778Z",
        "duration": 0.333,
        "timestamp_second": 441.747,
        "relative_time": 8.1805,
        "index": 50
    },
    {
        "type": "idle",
        "timestamp": "2024-10-18T02:59:29.118Z",
        "duration": 3.1479999999999997,
        "timestamp_second": 445.087,
        "relative_time": 8.242351851851852,
        "index": 51
    },
    {
        "type": "mouseMovement",
        "totalMouseMovement": 373.2892374927105,
        "timestamp": "2024-10-18T02:59:29.260Z",
        "duration": 0.632,
        "timestamp_second": 445.229,
        "relative_time": 8.244981481481481,
        "index": 52
    },
    {
        "type": "click",
        "e": "click",
        "timestamp": "2024-10-18T02:59:30.302Z",
        "target": "TEXTAREA",
        "x": 365,
        "y": 327,
        "timestamp_second": 446.271,
        "relative_time": 8.264277777777778,
        "index": 53
    },
    {
        "type": "paste",
        "timestamp": "2024-10-18T02:59:30.667Z",
        "text": "$20",
        "textLength": 3,
        "timestamp_second": 446.636,
        "relative_time": 8.271037037037038,
        "index": 54
    },
    {
        "type": "mouseMovement",
        "totalMouseMovement": 346.81174367201857,
        "timestamp": "2024-10-18T02:59:31.210Z",
        "duration": 0.047,
        "timestamp_second": 447.179,
        "relative_time": 8.281092592592593,
        "index": 55
    },
    {
        "type": "idle",
        "timestamp": "2024-10-18T02:59:34.257Z",
        "duration": 3.769,
        "timestamp_second": 450.226,
        "relative_time": 8.33751851851852,
        "index": 56
    },
    {
        "type": "mouseMovement",
        "totalMouseMovement": 403.20548935948136,
        "timestamp": "2024-10-18T02:59:35.026Z",
        "duration": 0.777,
        "timestamp_second": 450.995,
        "relative_time": 8.351759259259259,
        "index": 57
    },
    {
        "type": "click",
        "e": "click",
        "timestamp": "2024-10-18T02:59:36.234Z",
        "target": "TEXTAREA",
        "x": 333,
        "y": 360,
        "timestamp_second": 452.203,
        "relative_time": 8.374129629629628,
        "index": 58
    },
    {
        "type": "paste",
        "timestamp": "2024-10-18T02:59:36.639Z",
        "text": "Tuesday to Friday",
        "textLength": 17,
        "timestamp_second": 452.608,
        "relative_time": 8.381629629629629,
        "index": 59
    },
    {
        "type": "mousewheel",
        "timestamp": "2024-10-18T02:59:37.242Z",
        "deltaY": 304,
        "yDirection": 1,
        "duration": 1.043,
        "timestamp_second": 453.211,
        "relative_time": 8.392796296296297,
        "index": 60
    },
    {
        "type": "mouseMovement",
        "totalMouseMovement": 413.99179392680526,
        "timestamp": "2024-10-18T02:59:38.606Z",
        "duration": 0.052,
        "timestamp_second": 454.575,
        "relative_time": 8.418055555555554,
        "index": 61
    },
    {
        "type": "scroll",
        "timestamp": "2024-10-18T02:59:38.790Z",
        "deltaY": 0,
        "yDirection": 0,
        "timestamp_second": 454.759,
        "relative_time": 8.421462962962963,
        "index": 62
    },
    {
        "type": "idle",
        "timestamp": "2024-10-18T02:59:41.676Z",
        "duration": 5.689,
        "timestamp_second": 457.645,
        "relative_time": 8.474907407407407,
        "index": 63
    },
    {
        "type": "mouseMovement",
        "totalMouseMovement": 550.8738989552021,
        "timestamp": "2024-10-18T02:59:44.347Z",
        "duration": 0.849,
        "timestamp_second": 460.316,
        "relative_time": 8.52437037037037,
        "index": 64
    },
    {
        "type": "click",
        "e": "click",
        "timestamp": "2024-10-18T02:59:45.642Z",
        "target": "TEXTAREA",
        "x": 263,
        "y": 219,
        "timestamp_second": 461.611,
        "relative_time": 8.548351851851852,
        "index": 65
    },
    {
        "type": "paste",
        "timestamp": "2024-10-18T02:59:45.881Z",
        "text": "Rundetaarn",
        "textLength": 10,
        "timestamp_second": 461.85,
        "relative_time": 8.552777777777779,
        "index": 66
    },
    {
        "type": "mouseMovement",
        "totalMouseMovement": 489.4325643026932,
        "timestamp": "2024-10-18T02:59:46.386Z",
        "duration": 0.074,
        "timestamp_second": 462.355,
        "relative_time": 8.56212962962963,
        "index": 67
    },
    {
        "type": "idle",
        "timestamp": "2024-10-18T02:59:49.461Z",
        "duration": 3.934,
        "timestamp_second": 465.43,
        "relative_time": 8.619074074074074,
        "index": 68
    },
    {
        "type": "mouseMovement",
        "totalMouseMovement": 331.09535459506515,
        "timestamp": "2024-10-18T02:59:50.394Z",
        "duration": 0.53,
        "timestamp_second": 466.363,
        "relative_time": 8.636351851851853,
        "index": 69
    },
    {
        "type": "click",
        "e": "click",
        "timestamp": "2024-10-18T02:59:51.412Z",
        "target": "TEXTAREA",
        "x": 328,
        "y": 266,
        "timestamp_second": 467.381,
        "relative_time": 8.655203703703704,
        "index": 70
    },
    {
        "type": "paste",
        "timestamp": "2024-10-18T02:59:51.493Z",
        "text": "17th-century astronomy tower",
        "textLength": 28,
        "timestamp_second": 467.462,
        "relative_time": 8.656703703703704,
        "index": 71
    },
    {
        "type": "mousewheel",
        "timestamp": "2024-10-18T02:59:52.017Z",
        "deltaY": 1204,
        "yDirection": 2,
        "duration": 1.623,
        "timestamp_second": 467.986,
        "relative_time": 8.666407407407407,
        "index": 72
    },
    {
        "type": "scroll",
        "timestamp": "2024-10-18T02:59:54.144Z",
        "deltaY": 0,
        "yDirection": 0,
        "timestamp_second": 470.113,
        "relative_time": 8.705796296296295,
        "index": 73
    },
    {
        "type": "mousewheel",
        "timestamp": "2024-10-18T02:59:54.412Z",
        "deltaY": 958,
        "yDirection": 1,
        "duration": 1.893,
        "timestamp_second": 470.381,
        "relative_time": 8.710759259259259,
        "index": 74
    },
    {
        "type": "mousewheel",
        "timestamp": "2024-10-18T02:59:56.321Z",
        "deltaY": 0,
        "yDirection": 0,
        "duration": 0.0,
        "timestamp_second": 472.29,
        "relative_time": 8.746111111111112,
        "index": 75
    },
    {
        "type": "mousewheel",
        "timestamp": "2024-10-18T02:59:56.556Z",
        "deltaY": 377,
        "yDirection": 1,
        "duration": 1.413,
        "timestamp_second": 472.525,
        "relative_time": 8.750462962962963,
        "index": 76
    },
    {
        "type": "scroll",
        "timestamp": "2024-10-18T02:59:58.474Z",
        "deltaY": 0,
        "yDirection": 0,
        "timestamp_second": 474.443,
        "relative_time": 8.78598148148148,
        "index": 77
    },
    {
        "type": "mouseMovement",
        "totalMouseMovement": 872.9669990816801,
        "timestamp": "2024-10-18T02:59:59.298Z",
        "duration": 4.331,
        "timestamp_second": 475.267,
        "relative_time": 8.80124074074074,
        "index": 78
    },
    {
        "type": "click",
        "e": "click",
        "timestamp": "2024-10-18T03:00:04.059Z",
        "target": "TEXTAREA",
        "x": 366,
        "y": 227,
        "timestamp_second": 480.028,
        "relative_time": 8.889407407407408,
        "index": 79
    },
    {
        "type": "paste",
        "timestamp": "2024-10-18T03:00:04.170Z",
        "text": "DKK 40",
        "textLength": 6,
        "timestamp_second": 480.139,
        "relative_time": 8.891462962962963,
        "index": 80
    },
    {
        "type": "mouseMovement",
        "totalMouseMovement": 404.70457430901115,
        "timestamp": "2024-10-18T03:00:04.597Z",
        "duration": 0.065,
        "timestamp_second": 480.566,
        "relative_time": 8.89937037037037,
        "index": 81
    },
    {
        "type": "idle",
        "timestamp": "2024-10-18T03:00:07.676Z",
        "duration": 3.351,
        "timestamp_second": 483.645,
        "relative_time": 8.956388888888888,
        "index": 82
    },
    {
        "type": "mouseMovement",
        "totalMouseMovement": 463.78044853828214,
        "timestamp": "2024-10-18T03:00:08.013Z",
        "duration": 0.565,
        "timestamp_second": 483.982,
        "relative_time": 8.96262962962963,
        "index": 83
    },
    {
        "type": "click",
        "e": "click",
        "timestamp": "2024-10-18T03:00:09.000Z",
        "target": "TEXTAREA",
        "x": 300,
        "y": 261,
        "timestamp_second": 484.969,
        "relative_time": 8.980907407407408,
        "index": 84
    },
    {
        "type": "paste",
        "timestamp": "2024-10-18T03:00:09.050Z",
        "text": "Open all week",
        "textLength": 13,
        "timestamp_second": 485.019,
        "relative_time": 8.981833333333334,
        "index": 85
    },
    {
        "type": "mouseMovement",
        "totalMouseMovement": 123.84952442161557,
        "timestamp": "2024-10-18T03:00:09.643Z",
        "duration": 0.065,
        "timestamp_second": 485.612,
        "relative_time": 8.992814814814814,
        "index": 86
    },
    {
        "type": "mousewheel",
        "timestamp": "2024-10-18T03:00:09.940Z",
        "deltaY": 152,
        "yDirection": 1,
        "duration": 0.384,
        "timestamp_second": 485.909,
        "relative_time": 8.998314814814815,
        "index": 87
    },
    {
        "type": "mouseMovement",
        "totalMouseMovement": 387.49482173414617,
        "timestamp": "2024-10-18T03:00:10.626Z",
        "duration": 0.061,
        "timestamp_second": 486.595,
        "relative_time": 9.011018518518519,
        "index": 88
    },
    {
        "type": "scroll",
        "timestamp": "2024-10-18T03:00:10.836Z",
        "deltaY": 1,
        "yDirection": 1,
        "timestamp_second": 486.805,
        "relative_time": 9.014907407407408,
        "index": 89
    },
    {
        "type": "mouseMovement",
        "totalMouseMovement": 298.24837383284466,
        "timestamp": "2024-10-18T03:00:11.657Z",
        "duration": 0.233,
        "timestamp_second": 487.626,
        "relative_time": 9.030111111111111,
        "index": 90
    },
    {
        "type": "mousewheel",
        "timestamp": "2024-10-18T03:00:12.207Z",
        "deltaY": 1281,
        "yDirection": 2,
        "duration": 2.23,
        "timestamp_second": 488.176,
        "relative_time": 9.040296296296296,
        "index": 91
    },
    {
        "type": "scroll",
        "timestamp": "2024-10-18T03:00:14.941Z",
        "deltaY": 1,
        "yDirection": 2,
        "timestamp_second": 490.91,
        "relative_time": 9.090925925925927,
        "index": 92
    },
    {
        "type": "mousewheel",
        "timestamp": "2024-10-18T03:00:15.106Z",
        "deltaY": 47,
        "yDirection": 2,
        "duration": 0.179,
        "timestamp_second": 491.075,
        "relative_time": 9.09398148148148,
        "index": 93
    },
    {
        "type": "mousewheel",
        "timestamp": "2024-10-18T03:00:15.662Z",
        "deltaY": 1216,
        "yDirection": 1,
        "duration": 1.954,
        "timestamp_second": 491.631,
        "relative_time": 9.104277777777778,
        "index": 94
    },
    {
        "type": "mousewheel",
        "timestamp": "2024-10-18T03:00:17.633Z",
        "deltaY": 0,
        "yDirection": 0,
        "duration": 0.0,
        "timestamp_second": 493.602,
        "relative_time": 9.140777777777776,
        "index": 95
    },
    {
        "type": "mouseMovement",
        "totalMouseMovement": 170.6067758982681,
        "timestamp": "2024-10-18T03:00:17.873Z",
        "duration": 0.177,
        "timestamp_second": 493.842,
        "relative_time": 9.145222222222221,
        "index": 96
    },
    {
        "type": "scroll",
        "timestamp": "2024-10-18T03:00:18.136Z",
        "deltaY": 1,
        "yDirection": 2,
        "timestamp_second": 494.105,
        "relative_time": 9.150092592592593,
        "index": 97
    },
    {
        "type": "mousewheel",
        "timestamp": "2024-10-18T03:00:18.985Z",
        "deltaY": 209,
        "yDirection": 2,
        "duration": 0.231,
        "timestamp_second": 494.954,
        "relative_time": 9.165814814814816,
        "index": 98
    },
    {
        "type": "mousewheel",
        "timestamp": "2024-10-18T03:00:19.382Z",
        "deltaY": 360,
        "yDirection": 1,
        "duration": 2.103,
        "timestamp_second": 495.351,
        "relative_time": 9.173166666666667,
        "index": 99
    },
    {
        "type": "mouseMovement",
        "totalMouseMovement": 424.41129999696204,
        "timestamp": "2024-10-18T03:00:21.713Z",
        "duration": 0.061,
        "timestamp_second": 497.682,
        "relative_time": 9.216333333333333,
        "index": 100
    },
    {
        "type": "scroll",
        "timestamp": "2024-10-18T03:00:21.991Z",
        "deltaY": 1,
        "yDirection": 1,
        "timestamp_second": 497.96,
        "relative_time": 9.221481481481481,
        "index": 101
    },
    {
        "type": "idle",
        "timestamp": "2024-10-18T03:00:24.787Z",
        "duration": 6.401,
        "timestamp_second": 500.756,
        "relative_time": 9.273259259259259,
        "index": 102
    },
    {
        "type": "mouseMovement",
        "totalMouseMovement": 508.3253110359692,
        "timestamp": "2024-10-18T03:00:28.176Z",
        "duration": 0.75,
        "timestamp_second": 504.145,
        "relative_time": 9.336018518518518,
        "index": 103
    },
    {
        "type": "click",
        "e": "click",
        "timestamp": "2024-10-18T03:00:29.378Z",
        "target": "TEXTAREA",
        "x": 242,
        "y": 225,
        "timestamp_second": 505.347,
        "relative_time": 9.358277777777777,
        "index": 104
    },
    {
        "type": "paste",
        "timestamp": "2024-10-18T03:00:29.461Z",
        "text": "Nyhavn",
        "textLength": 6,
        "timestamp_second": 505.43,
        "relative_time": 9.359814814814815,
        "index": 105
    },
    {
        "type": "mouseMovement",
        "totalMouseMovement": 496.87525173101676,
        "timestamp": "2024-10-18T03:00:29.886Z",
        "duration": 0.054,
        "timestamp_second": 505.855,
        "relative_time": 9.367685185185186,
        "index": 106
    },
    {
        "type": "idle",
        "timestamp": "2024-10-18T03:00:32.954Z",
        "duration": 3.666,
        "timestamp_second": 508.923,
        "relative_time": 9.4245,
        "index": 107
    },
    {
        "type": "mouseMovement",
        "totalMouseMovement": 286.71647718828535,
        "timestamp": "2024-10-18T03:00:33.606Z",
        "duration": 0.447,
        "timestamp_second": 509.575,
        "relative_time": 9.436574074074073,
        "index": 108
    },
    {
        "type": "click",
        "e": "click",
        "timestamp": "2024-10-18T03:00:34.484Z",
        "target": "TEXTAREA",
        "x": 412,
        "y": 263,
        "timestamp_second": 510.453,
        "relative_time": 9.452833333333333,
        "index": 109
    },
    {
        "type": "paste",
        "timestamp": "2024-10-18T03:00:34.592Z",
        "text": "Iconic and picturesque area with colorful buildings and historic boats",
        "textLength": 70,
        "timestamp_second": 510.561,
        "relative_time": 9.454833333333333,
        "index": 110
    },
    {
        "type": "mouseMovement",
        "totalMouseMovement": 2419.0504872009406,
        "timestamp": "2024-10-18T03:00:35.118Z",
        "duration": 5.862,
        "timestamp_second": 511.087,
        "relative_time": 9.464574074074074,
        "index": 111
    },
    {
        "type": "click",
        "e": "click",
        "timestamp": "2024-10-18T03:00:41.406Z",
        "target": "TEXTAREA",
        "x": 284,
        "y": 338,
        "timestamp_second": 517.375,
        "relative_time": 9.581018518518517,
        "index": 112
    },
    {
        "type": "keypress",
        "timestamp": "2024-10-18T03:00:41.524Z",
        "duration": 0.782,
        "key_list": "Free",
        "keyCode_list": [
            70,
            114,
            101,
            101
        ],
        "target": "TEXTAREA",
        "key_count": 4,
        "timestamp_second": 517.493,
        "relative_time": 9.583203703703704,
        "index": 113
    },
    {
        "type": "mouseMovement",
        "totalMouseMovement": 457.8632776567065,
        "timestamp": "2024-10-18T03:00:42.897Z",
        "duration": 1.649,
        "timestamp_second": 518.866,
        "relative_time": 9.608629629629629,
        "index": 114
    },
    {
        "type": "highlight",
        "timestamp": "2024-10-18T03:00:44.562Z",
        "highlightedText": "Open all week",
        "highlightedTextLength": 13,
        "timestamp_second": 520.531,
        "relative_time": 9.639462962962963,
        "index": 115
    },
    {
        "type": "click",
        "e": "click",
        "timestamp": "2024-10-18T03:00:44.566Z",
        "target": "TR",
        "x": 176,
        "y": 57,
        "timestamp_second": 520.535,
        "relative_time": 9.639537037037037,
        "index": 116
    },
    {
        "type": "copy",
        "timestamp": "2024-10-18T03:00:44.937Z",
        "text": "Open all week",
        "textLength": 13,
        "timestamp_second": 520.906,
        "relative_time": 9.646407407407406,
        "index": 117
    },
    {
        "type": "mouseMovement",
        "totalMouseMovement": 386.6741610607278,
        "timestamp": "2024-10-18T03:00:45.121Z",
        "duration": 0.788,
        "timestamp_second": 521.09,
        "relative_time": 9.649814814814816,
        "index": 118
    },
    {
        "type": "click",
        "e": "click",
        "timestamp": "2024-10-18T03:00:46.348Z",
        "target": "TEXTAREA",
        "x": 321,
        "y": 372,
        "timestamp_second": 522.317,
        "relative_time": 9.672537037037038,
        "index": 119
    },
    {
        "type": "paste",
        "timestamp": "2024-10-18T03:00:46.454Z",
        "text": "Open all week",
        "textLength": 13,
        "timestamp_second": 522.423,
        "relative_time": 9.6745,
        "index": 120
    },
    {
        "type": "mousewheel",
        "timestamp": "2024-10-18T03:00:46.854Z",
        "deltaY": 321,
        "yDirection": 1,
        "duration": 0.637,
        "timestamp_second": 522.823,
        "relative_time": 9.681907407407406,
        "index": 121
    },
    {
        "type": "mouseMovement",
        "totalMouseMovement": 373.3009524515437,
        "timestamp": "2024-10-18T03:00:47.745Z",
        "duration": 0.046,
        "timestamp_second": 523.714,
        "relative_time": 9.698407407407409,
        "index": 122
    },
    {
        "type": "scroll",
        "timestamp": "2024-10-18T03:00:47.991Z",
        "deltaY": 0,
        "yDirection": 0,
        "timestamp_second": 523.96,
        "relative_time": 9.702962962962964,
        "index": 123
    },
    {
        "type": "idle",
        "timestamp": "2024-10-18T03:00:50.794Z",
        "duration": 5.179,
        "timestamp_second": 526.763,
        "relative_time": 9.754870370370371,
        "index": 124
    },
    {
        "type": "mouseMovement",
        "totalMouseMovement": 490.9190346532596,
        "timestamp": "2024-10-18T03:00:52.970Z",
        "duration": 0.584,
        "timestamp_second": 528.939,
        "relative_time": 9.795166666666667,
        "index": 125
    },
    {
        "type": "click",
        "e": "click",
        "timestamp": "2024-10-18T03:00:54.043Z",
        "target": "TEXTAREA",
        "x": 304,
        "y": 201,
        "timestamp_second": 530.012,
        "relative_time": 9.815037037037037,
        "index": 126
    },
    {
        "type": "paste",
        "timestamp": "2024-10-18T03:00:54.097Z",
        "text": "Tivoli Gardens",
        "textLength": 14,
        "timestamp_second": 530.066,
        "relative_time": 9.816037037037036,
        "index": 127
    },
    {
        "type": "mouseMovement",
        "totalMouseMovement": 429.38270289680077,
        "timestamp": "2024-10-18T03:00:54.597Z",
        "duration": 0.053,
        "timestamp_second": 530.566,
        "relative_time": 9.825296296296298,
        "index": 128
    },
    {
        "type": "idle",
        "timestamp": "2024-10-18T03:00:57.651Z",
        "duration": 3.4989999999999997,
        "timestamp_second": 533.62,
        "relative_time": 9.88185185185185,
        "index": 129
    },
    {
        "type": "mouseMovement",
        "totalMouseMovement": 439.2253293413087,
        "timestamp": "2024-10-18T03:00:58.149Z",
        "duration": 0.816,
        "timestamp_second": 534.118,
        "relative_time": 9.891074074074075,
        "index": 130
    },
    {
        "type": "click",
        "e": "click",
        "timestamp": "2024-10-18T03:00:59.401Z",
        "target": "TEXTAREA",
        "x": 283,
        "y": 251,
        "timestamp_second": 535.37,
        "relative_time": 9.914259259259259,
        "index": 131
    },
    {
        "type": "paste",
        "timestamp": "2024-10-18T03:00:59.510Z",
        "text": "Enchanting atmosphere with beautiful gardens and thrilling amusement park rides",
        "textLength": 79,
        "timestamp_second": 535.479,
        "relative_time": 9.916277777777777,
        "index": 132
    },
    {
        "type": "mouseMovement",
        "totalMouseMovement": 783.0295789273805,
        "timestamp": "2024-10-18T03:01:00.148Z",
        "duration": 3.08,
        "timestamp_second": 536.117,
        "relative_time": 9.928092592592593,
        "index": 133
    },
    {
        "type": "click",
        "e": "click",
        "timestamp": "2024-10-18T03:01:03.819Z",
        "target": "TEXTAREA",
        "x": 298,
        "y": 317,
        "timestamp_second": 539.788,
        "relative_time": 9.996074074074073,
        "index": 134
    },
    {
        "type": "keypress",
        "timestamp": "2024-10-18T03:01:04.068Z",
        "duration": 0.778,
        "key_list": "Free",
        "keyCode_list": [
            70,
            114,
            101,
            101
        ],
        "target": "TEXTAREA",
        "key_count": 4,
        "timestamp_second": 540.037,
        "relative_time": 10.000685185185185,
        "index": 135
    },
    {
        "type": "mouseMovement",
        "totalMouseMovement": 373.1659389219203,
        "timestamp": "2024-10-18T03:01:05.447Z",
        "duration": 0.345,
        "timestamp_second": 541.416,
        "relative_time": 10.026222222222223,
        "index": 136
    },
    {
        "type": "idle",
        "timestamp": "2024-10-18T03:01:08.797Z",
        "duration": 3.202,
        "timestamp_second": 544.766,
        "relative_time": 10.088259259259258,
        "index": 137
    },
    {
        "type": "mouseMovement",
        "totalMouseMovement": 369.61798825249207,
        "timestamp": "2024-10-18T03:01:08.994Z",
        "duration": 0.661,
        "timestamp_second": 544.963,
        "relative_time": 10.091907407407406,
        "index": 138
    },
    {
        "type": "click",
        "e": "click",
        "timestamp": "2024-10-18T03:01:10.083Z",
        "target": "TEXTAREA",
        "x": 434,
        "y": 351,
        "timestamp_second": 546.052,
        "relative_time": 10.112074074074075,
        "index": 139
    },
    {
        "type": "paste",
        "timestamp": "2024-10-18T03:01:10.293Z",
        "text": "Monday to Saturday",
        "textLength": 18,
        "timestamp_second": 546.262,
        "relative_time": 10.11596296296296,
        "index": 140
    },
    {
        "type": "mousewheel",
        "timestamp": "2024-10-18T03:01:11.055Z",
        "deltaY": 262,
        "yDirection": 1,
        "duration": 0.831,
        "timestamp_second": 547.024,
        "relative_time": 10.130074074074075,
        "index": 141
    },
    {
        "type": "mouseMovement",
        "totalMouseMovement": 270.2966401112062,
        "timestamp": "2024-10-18T03:01:12.097Z",
        "duration": 0.039,
        "timestamp_second": 548.066,
        "relative_time": 10.149370370370372,
        "index": 142
    },
    {
        "type": "scroll",
        "timestamp": "2024-10-18T03:01:12.386Z",
        "deltaY": 1,
        "yDirection": 1,
        "timestamp_second": 548.355,
        "relative_time": 10.154722222222222,
        "index": 143
    },
    {
        "type": "idle",
        "timestamp": "2024-10-18T03:01:15.151Z",
        "duration": 4.35,
        "timestamp_second": 551.12,
        "relative_time": 10.205925925925927,
        "index": 144
    },
    {
        "type": "mouseMovement",
        "totalMouseMovement": 582.4061512015687,
        "timestamp": "2024-10-18T03:01:16.486Z",
        "duration": 0.829,
        "timestamp_second": 552.455,
        "relative_time": 10.230648148148148,
        "index": 145
    },
    {
        "type": "click",
        "e": "click",
        "timestamp": "2024-10-18T03:01:17.768Z",
        "target": "TEXTAREA",
        "x": 252,
        "y": 267,
        "timestamp_second": 553.737,
        "relative_time": 10.254388888888888,
        "index": 146
    },
    {
        "type": "paste",
        "timestamp": "2024-10-18T03:01:17.811Z",
        "text": "Skagens Museum",
        "textLength": 14,
        "timestamp_second": 553.78,
        "relative_time": 10.255185185185185,
        "index": 147
    },
    {
        "type": "mouseMovement",
        "totalMouseMovement": 493.25049690894593,
        "timestamp": "2024-10-18T03:01:18.191Z",
        "duration": 0.074,
        "timestamp_second": 554.16,
        "relative_time": 10.26222222222222,
        "index": 148
    },
    {
        "type": "idle",
        "timestamp": "2024-10-18T03:01:21.266Z",
        "duration": 3.814,
        "timestamp_second": 557.235,
        "relative_time": 10.319166666666666,
        "index": 149
    },
    {
        "type": "mouseMovement",
        "totalMouseMovement": 383.1897573797578,
        "timestamp": "2024-10-18T03:01:22.079Z",
        "duration": 1.164,
        "timestamp_second": 558.048,
        "relative_time": 10.334222222222223,
        "index": 150
    },
    {
        "type": "click",
        "e": "click",
        "timestamp": "2024-10-18T03:01:23.697Z",
        "target": "TEXTAREA",
        "x": 323,
        "y": 291,
        "timestamp_second": 559.666,
        "relative_time": 10.364185185185185,
        "index": 151
    },
    {
        "type": "paste",
        "timestamp": "2024-10-18T03:01:23.777Z",
        "text": "Renowned art museum showcasing the works of the Skagen Painters",
        "textLength": 63,
        "timestamp_second": 559.746,
        "relative_time": 10.365666666666666,
        "index": 152
    },
    {
        "type": "mouseMovement",
        "totalMouseMovement": 433.7643394609622,
        "timestamp": "2024-10-18T03:01:24.159Z",
        "duration": 0.083,
        "timestamp_second": 560.128,
        "relative_time": 10.372740740740742,
        "index": 153
    },
    {
        "type": "idle",
        "timestamp": "2024-10-18T03:01:27.258Z",
        "duration": 3.315,
        "timestamp_second": 563.227,
        "relative_time": 10.43012962962963,
        "index": 154
    },
    {
        "type": "mouseMovement",
        "totalMouseMovement": 647.3850723998039,
        "timestamp": "2024-10-18T03:01:27.557Z",
        "duration": 0.67,
        "timestamp_second": 563.526,
        "relative_time": 10.435666666666666,
        "index": 155
    },
    {
        "type": "click",
        "e": "click",
        "timestamp": "2024-10-18T03:01:28.681Z",
        "target": "TEXTAREA",
        "x": 286,
        "y": 369,
        "timestamp_second": 564.65,
        "relative_time": 10.45648148148148,
        "index": 156
    },
    {
        "type": "paste",
        "timestamp": "2024-10-18T03:01:28.768Z",
        "text": "200 DKK",
        "textLength": 7,
        "timestamp_second": 564.737,
        "relative_time": 10.458092592592592,
        "index": 157
    },
    {
        "type": "mouseMovement",
        "totalMouseMovement": 912.4564600899321,
        "timestamp": "2024-10-18T03:01:29.085Z",
        "duration": 3.617,
        "timestamp_second": 565.054,
        "relative_time": 10.463962962962963,
        "index": 158
    },
    {
        "type": "click",
        "e": "click",
        "timestamp": "2024-10-18T03:01:33.123Z",
        "target": "TEXTAREA",
        "x": 309,
        "y": 416,
        "timestamp_second": 569.092,
        "relative_time": 10.53874074074074,
        "index": 159
    },
    {
        "type": "paste",
        "timestamp": "2024-10-18T03:01:33.260Z",
        "text": "Tuesday to Friday",
        "textLength": 17,
        "timestamp_second": 569.229,
        "relative_time": 10.541277777777779,
        "index": 160
    },
    {
        "type": "mousewheel",
        "timestamp": "2024-10-18T03:01:33.639Z",
        "deltaY": 419,
        "yDirection": 1,
        "duration": 0.328,
        "timestamp_second": 569.608,
        "relative_time": 10.548296296296297,
        "index": 161
    },
    {
        "type": "click",
        "e": "click",
        "timestamp": "2024-10-18T03:01:34.179Z",
        "target": "TEXTAREA",
        "x": 309,
        "y": 416,
        "timestamp_second": 570.148,
        "relative_time": 10.558296296296296,
        "index": 162
    },
    {
        "type": "mousewheel",
        "timestamp": "2024-10-18T03:01:34.318Z",
        "deltaY": 88,
        "yDirection": 2,
        "duration": 0.27,
        "timestamp_second": 570.287,
        "relative_time": 10.56087037037037,
        "index": 163
    },
    {
        "type": "mouseMovement",
        "totalMouseMovement": 431.31554054972,
        "timestamp": "2024-10-18T03:01:34.837Z",
        "duration": 0.066,
        "timestamp_second": 570.806,
        "relative_time": 10.570481481481481,
        "index": 164
    },
    {
        "type": "scroll",
        "timestamp": "2024-10-18T03:01:35.103Z",
        "deltaY": 0,
        "yDirection": 0,
        "timestamp_second": 571.072,
        "relative_time": 10.575407407407408,
        "index": 165
    },
    {
        "type": "idle",
        "timestamp": "2024-10-18T03:01:37.903Z",
        "duration": 4.878,
        "timestamp_second": 573.872,
        "relative_time": 10.627259259259258,
        "index": 166
    },
    {
        "type": "mouseMovement",
        "totalMouseMovement": 332.7295083741701,
        "timestamp": "2024-10-18T03:01:39.781Z",
        "duration": 0.497,
        "timestamp_second": 575.75,
        "relative_time": 10.662037037037036,
        "index": 167
    },
    {
        "type": "click",
        "e": "click",
        "timestamp": "2024-10-18T03:01:40.709Z",
        "target": "TEXTAREA",
        "x": 371,
        "y": 216,
        "timestamp_second": 576.678,
        "relative_time": 10.679222222222222,
        "index": 168
    },
    {
        "type": "paste",
        "timestamp": "2024-10-18T03:01:40.847Z",
        "text": "LEGOLAND Billund Resort",
        "textLength": 23,
        "timestamp_second": 576.816,
        "relative_time": 10.681777777777778,
        "index": 169
    },
    {
        "type": "mouseMovement",
        "totalMouseMovement": 293.98957333486396,
        "timestamp": "2024-10-18T03:01:41.229Z",
        "duration": 0.048,
        "timestamp_second": 577.198,
        "relative_time": 10.688851851851851,
        "index": 170
    },
    {
        "type": "idle",
        "timestamp": "2024-10-18T03:01:44.281Z",
        "duration": 3.899,
        "timestamp_second": 580.25,
        "relative_time": 10.74537037037037,
        "index": 171
    },
    {
        "type": "mouseMovement",
        "totalMouseMovement": 289.16233129172906,
        "timestamp": "2024-10-18T03:01:45.176Z",
        "duration": 0.599,
        "timestamp_second": 581.145,
        "relative_time": 10.761944444444444,
        "index": 172
    },
    {
        "type": "click",
        "e": "click",
        "timestamp": "2024-10-18T03:01:46.199Z",
        "target": "TEXTAREA",
        "x": 424,
        "y": 263,
        "timestamp_second": 582.168,
        "relative_time": 10.780888888888889,
        "index": 173
    },
    {
        "type": "paste",
        "timestamp": "2024-10-18T03:01:46.517Z",
        "text": "Birthplace of the LEGO brick, offers a world of fun and creativity",
        "textLength": 66,
        "timestamp_second": 582.486,
        "relative_time": 10.786777777777777,
        "index": 174
    },
    {
        "type": "mouseMovement",
        "totalMouseMovement": 310.0167720328791,
        "timestamp": "2024-10-18T03:01:47.011Z",
        "duration": 0.055,
        "timestamp_second": 582.98,
        "relative_time": 10.795925925925927,
        "index": 175
    },
    {
        "type": "idle",
        "timestamp": "2024-10-18T03:01:50.078Z",
        "duration": 3.186,
        "timestamp_second": 586.047,
        "relative_time": 10.852722222222223,
        "index": 176
    },
    {
        "type": "mouseMovement",
        "totalMouseMovement": 389.55036871673656,
        "timestamp": "2024-10-18T03:01:50.253Z",
        "duration": 0.887,
        "timestamp_second": 586.222,
        "relative_time": 10.855962962962963,
        "index": 177
    },
    {
        "type": "click",
        "e": "click",
        "timestamp": "2024-10-18T03:01:51.578Z",
        "target": "TEXTAREA",
        "x": 377,
        "y": 353,
        "timestamp_second": 587.547,
        "relative_time": 10.8805,
        "index": 178
    },
    {
        "type": "paste",
        "timestamp": "2024-10-18T03:01:51.919Z",
        "text": "299 DKK",
        "textLength": 7,
        "timestamp_second": 587.888,
        "relative_time": 10.886814814814816,
        "index": 179
    },
    {
        "type": "mouseMovement",
        "totalMouseMovement": 322.4275955390367,
        "timestamp": "2024-10-18T03:01:52.268Z",
        "duration": 0.049,
        "timestamp_second": 588.237,
        "relative_time": 10.893277777777776,
        "index": 180
    },
    {
        "type": "idle",
        "timestamp": "2024-10-18T03:01:55.330Z",
        "duration": 6.013,
        "timestamp_second": 591.299,
        "relative_time": 10.949981481481482,
        "index": 181
    },
    {
        "type": "mouseMovement",
        "totalMouseMovement": 387.13761188248463,
        "timestamp": "2024-10-18T03:01:58.330Z",
        "duration": 0.715,
        "timestamp_second": 594.299,
        "relative_time": 11.005537037037037,
        "index": 182
    },
    {
        "type": "click",
        "e": "click",
        "timestamp": "2024-10-18T03:01:59.475Z",
        "target": "TEXTAREA",
        "x": 309,
        "y": 387,
        "timestamp_second": 595.444,
        "relative_time": 11.02674074074074,
        "index": 183
    },
    {
        "type": "paste",
        "timestamp": "2024-10-18T03:01:59.625Z",
        "text": "Open all week",
        "textLength": 13,
        "timestamp_second": 595.594,
        "relative_time": 11.029518518518518,
        "index": 184
    },
    {
        "type": "mousewheel",
        "timestamp": "2024-10-18T03:02:00.110Z",
        "deltaY": 391,
        "yDirection": 1,
        "duration": 1.07,
        "timestamp_second": 596.079,
        "relative_time": 11.038499999999999,
        "index": 185
    },
    {
        "type": "mousewheel",
        "timestamp": "2024-10-18T03:02:01.626Z",
        "deltaY": 2609,
        "yDirection": 2,
        "duration": 3.982,
        "timestamp_second": 597.595,
        "relative_time": 11.066574074074074,
        "index": 186
    },
    {
        "type": "scroll",
        "timestamp": "2024-10-18T03:02:06.119Z",
        "deltaY": 0,
        "yDirection": 0,
        "timestamp_second": 602.088,
        "relative_time": 11.149777777777777,
        "index": 187
    },
    {
        "type": "mousewheel",
        "timestamp": "2024-10-18T03:02:06.306Z",
        "deltaY": 138,
        "yDirection": 2,
        "duration": 0.366,
        "timestamp_second": 602.275,
        "relative_time": 11.15324074074074,
        "index": 188
    },
    {
        "type": "mouseMovement",
        "totalMouseMovement": 144.59132951878564,
        "timestamp": "2024-10-18T03:02:06.967Z",
        "duration": 0.155,
        "timestamp_second": 602.936,
        "relative_time": 11.165481481481482,
        "index": 189
    },
    {
        "type": "scroll",
        "timestamp": "2024-10-18T03:02:07.176Z",
        "deltaY": 1,
        "yDirection": 2,
        "timestamp_second": 603.145,
        "relative_time": 11.169351851851852,
        "index": 190
    },
    {
        "type": "mouseMovement",
        "totalMouseMovement": 304.32131576609754,
        "timestamp": "2024-10-18T03:02:07.540Z",
        "duration": 0.043,
        "timestamp_second": 603.509,
        "relative_time": 11.176092592592592,
        "index": 191
    },
    {
        "type": "idle",
        "timestamp": "2024-10-18T03:02:10.585Z",
        "duration": 98.089,
        "timestamp_second": 606.554,
        "relative_time": 11.23248148148148,
        "index": 192
    },
    {
        "type": "mouseMovement",
        "totalMouseMovement": 297.763564827721,
        "timestamp": "2024-10-18T03:03:45.672Z",
        "duration": 0.214,
        "timestamp_second": 701.641,
        "relative_time": 12.99335185185185,
        "index": 193
    },
    {
        "type": "mousewheel",
        "timestamp": "2024-10-18T03:03:46.321Z",
        "deltaY": 2722,
        "yDirection": 1,
        "duration": 5.376,
        "timestamp_second": 702.29,
        "relative_time": 13.00537037037037,
        "index": 194
    },
    {
        "type": "mouseMovement",
        "totalMouseMovement": 169.72737891660654,
        "timestamp": "2024-10-18T03:03:52.173Z",
        "duration": 0.025,
        "timestamp_second": 708.142,
        "relative_time": 13.113740740740742,
        "index": 195
    },
    {
        "type": "scroll",
        "timestamp": "2024-10-18T03:03:52.199Z",
        "deltaY": 0,
        "yDirection": 0,
        "timestamp_second": 708.168,
        "relative_time": 13.114222222222221,
        "index": 196
    },
    {
        "type": "idle",
        "timestamp": "2024-10-18T03:03:55.217Z",
        "duration": 3.546,
        "timestamp_second": 711.186,
        "relative_time": 13.170111111111114,
        "index": 197
    },
    {
        "type": "mouseMovement",
        "totalMouseMovement": 280.0511222741916,
        "timestamp": "2024-10-18T03:03:55.761Z",
        "duration": 0.418,
        "timestamp_second": 711.73,
        "relative_time": 13.180185185185186,
        "index": 198
    },
    {
        "type": "click",
        "e": "click",
        "timestamp": "2024-10-18T03:03:56.592Z",
        "target": "TEXTAREA",
        "x": 378,
        "y": 199,
        "timestamp_second": 712.561,
        "relative_time": 13.195574074074074,
        "index": 199
    },
    {
        "type": "paste",
        "timestamp": "2024-10-18T03:03:56.998Z",
        "text": "Power sockets: Type A and Type K.",
        "textLength": 33,
        "timestamp_second": 712.967,
        "relative_time": 13.203092592592592,
        "index": 200
    },
    {
        "type": "mouseMovement",
        "totalMouseMovement": 321.33105214474926,
        "timestamp": "2024-10-18T03:03:57.578Z",
        "duration": 0.066,
        "timestamp_second": 713.547,
        "relative_time": 13.213833333333334,
        "index": 201
    },
    {
        "type": "idle",
        "timestamp": "2024-10-18T03:04:00.646Z",
        "duration": 22.329,
        "timestamp_second": 716.615,
        "relative_time": 13.270648148148148,
        "index": 202
    },
    {
        "type": "mouseMovement",
        "totalMouseMovement": 283.60454717676475,
        "timestamp": "2024-10-18T03:04:19.974Z",
        "duration": 0.367,
        "timestamp_second": 735.943,
        "relative_time": 13.628574074074074,
        "index": 203
    },
    {
        "type": "mousewheel",
        "timestamp": "2024-10-18T03:04:21.056Z",
        "deltaY": 2303,
        "yDirection": 2,
        "duration": 2.58,
        "timestamp_second": 737.025,
        "relative_time": 13.648611111111112,
        "index": 204
    },
    {
        "type": "mousewheel",
        "timestamp": "2024-10-18T03:04:23.653Z",
        "deltaY": 0,
        "yDirection": 0,
        "duration": 0.065,
        "timestamp_second": 739.622,
        "relative_time": 13.696703703703703,
        "index": 205
    },
    {
        "type": "scroll",
        "timestamp": "2024-10-18T03:04:24.232Z",
        "deltaY": 0,
        "yDirection": 0,
        "timestamp_second": 740.201,
        "relative_time": 13.707425925925925,
        "index": 206
    },
    {
        "type": "mousewheel",
        "timestamp": "2024-10-18T03:04:25.852Z",
        "deltaY": 9,
        "yDirection": 2,
        "duration": 0.132,
        "timestamp_second": 741.821,
        "relative_time": 13.737425925925924,
        "index": 207
    },
    {
        "type": "mousewheel",
        "timestamp": "2024-10-18T03:04:26.452Z",
        "deltaY": 0,
        "yDirection": 0,
        "duration": 0.181,
        "timestamp_second": 742.421,
        "relative_time": 13.748537037037037,
        "index": 208
    },
    {
        "type": "scroll",
        "timestamp": "2024-10-18T03:04:27.145Z",
        "deltaY": 0,
        "yDirection": 0,
        "timestamp_second": 743.114,
        "relative_time": 13.76137037037037,
        "index": 209
    },
    {
        "type": "mousewheel",
        "timestamp": "2024-10-18T03:04:29.137Z",
        "deltaY": 1501,
        "yDirection": 1,
        "duration": 1.327,
        "timestamp_second": 745.106,
        "relative_time": 13.798259259259261,
        "index": 210
    },
    {
        "type": "mousewheel",
        "timestamp": "2024-10-18T03:04:30.481Z",
        "deltaY": 1949,
        "yDirection": 2,
        "duration": 1.284,
        "timestamp_second": 746.45,
        "relative_time": 13.823148148148148,
        "index": 211
    },
    {
        "type": "scroll",
        "timestamp": "2024-10-18T03:04:32.274Z",
        "deltaY": 0,
        "yDirection": 0,
        "timestamp_second": 748.243,
        "relative_time": 13.856351851851853,
        "index": 212
    },
    {
        "type": "mouseMovement",
        "totalMouseMovement": 272.1140847038332,
        "timestamp": "2024-10-18T03:04:32.692Z",
        "duration": 0.036,
        "timestamp_second": 748.661,
        "relative_time": 13.864092592592591,
        "index": 213
    },
    {
        "type": "idle",
        "timestamp": "2024-10-18T03:04:35.738Z",
        "duration": 76.703,
        "timestamp_second": 751.707,
        "relative_time": 13.920499999999999,
        "index": 214
    },
    {
        "type": "mouseMovement",
        "totalMouseMovement": 453.07619673883164,
        "timestamp": "2024-10-18T03:05:49.431Z",
        "duration": 0.314,
        "timestamp_second": 825.4,
        "relative_time": 15.285185185185185,
        "index": 215
    },
    {
        "type": "mousewheel",
        "timestamp": "2024-10-18T03:05:50.061Z",
        "deltaY": 2817,
        "yDirection": 1,
        "duration": 4.083,
        "timestamp_second": 826.03,
        "relative_time": 15.29685185185185,
        "index": 216
    },
    {
        "type": "mouseMovement",
        "totalMouseMovement": 344.5142142167897,
        "timestamp": "2024-10-18T03:05:54.338Z",
        "duration": 0.302,
        "timestamp_second": 830.307,
        "relative_time": 15.376055555555556,
        "index": 217
    },
    {
        "type": "scroll",
        "timestamp": "2024-10-18T03:05:54.654Z",
        "deltaY": 0,
        "yDirection": 0,
        "timestamp_second": 830.623,
        "relative_time": 15.381907407407407,
        "index": 218
    },
    {
        "type": "mouseMovement",
        "totalMouseMovement": 30.17849076375569,
        "timestamp": "2024-10-18T03:05:54.731Z",
        "duration": 0.147,
        "timestamp_second": 830.7,
        "relative_time": 15.383333333333335,
        "index": 219
    },
    {
        "type": "click",
        "e": "click",
        "timestamp": "2024-10-18T03:05:55.396Z",
        "target": "TEXTAREA",
        "x": 369,
        "y": 187,
        "timestamp_second": 831.365,
        "relative_time": 15.395648148148148,
        "index": 220
    },
    {
        "type": "paste",
        "timestamp": "2024-10-18T03:05:55.822Z",
        "text": "Currency: Danish Krone (DKK). Euros are not widely accepted.",
        "textLength": 60,
        "timestamp_second": 831.791,
        "relative_time": 15.403537037037038,
        "index": 221
    },
    {
        "type": "mouseMovement",
        "totalMouseMovement": 358.06886912507616,
        "timestamp": "2024-10-18T03:05:56.326Z",
        "duration": 0.055,
        "timestamp_second": 832.295,
        "relative_time": 15.412870370370369,
        "index": 222
    },
    {
        "type": "idle",
        "timestamp": "2024-10-18T03:05:59.391Z",
        "duration": 5.019,
        "timestamp_second": 835.36,
        "relative_time": 15.46962962962963,
        "index": 223
    },
    {
        "type": "mouseMovement",
        "totalMouseMovement": 272.6633774377333,
        "timestamp": "2024-10-18T03:06:01.401Z",
        "duration": 0.168,
        "timestamp_second": 837.37,
        "relative_time": 15.506851851851852,
        "index": 224
    },
    {
        "type": "mousewheel",
        "timestamp": "2024-10-18T03:06:01.921Z",
        "deltaY": 3284,
        "yDirection": 2,
        "duration": 2.695,
        "timestamp_second": 837.89,
        "relative_time": 15.516481481481481,
        "index": 225
    },
    {
        "type": "scroll",
        "timestamp": "2024-10-18T03:06:05.128Z",
        "deltaY": 1,
        "yDirection": 2,
        "timestamp_second": 841.097,
        "relative_time": 15.575870370370371,
        "index": 226
    },
    {
        "type": "idle",
        "timestamp": "2024-10-18T03:06:07.637Z",
        "duration": 4.414,
        "timestamp_second": 843.606,
        "relative_time": 15.622333333333332,
        "index": 227
    },
    {
        "type": "mousewheel",
        "timestamp": "2024-10-18T03:06:09.046Z",
        "deltaY": 17,
        "yDirection": 1,
        "duration": 0.581,
        "timestamp_second": 845.015,
        "relative_time": 15.648425925925928,
        "index": 228
    },
    {
        "type": "scroll",
        "timestamp": "2024-10-18T03:06:10.135Z",
        "deltaY": 0,
        "yDirection": 0,
        "timestamp_second": 846.104,
        "relative_time": 15.668592592592592,
        "index": 229
    },
    {
        "type": "mousewheel",
        "timestamp": "2024-10-18T03:06:11.442Z",
        "deltaY": 24,
        "yDirection": 2,
        "duration": 0.167,
        "timestamp_second": 847.411,
        "relative_time": 15.692796296296297,
        "index": 230
    },
    {
        "type": "mousewheel",
        "timestamp": "2024-10-18T03:06:11.879Z",
        "deltaY": 26,
        "yDirection": 1,
        "duration": 0.23,
        "timestamp_second": 847.848,
        "relative_time": 15.700888888888889,
        "index": 231
    },
    {
        "type": "scroll",
        "timestamp": "2024-10-18T03:06:12.611Z",
        "deltaY": 2,
        "yDirection": 1,
        "timestamp_second": 848.58,
        "relative_time": 15.714444444444444,
        "index": 232
    },
    {
        "type": "mousewheel",
        "timestamp": "2024-10-18T03:06:12.726Z",
        "deltaY": 22,
        "yDirection": 1,
        "duration": 0.265,
        "timestamp_second": 848.695,
        "relative_time": 15.716574074074074,
        "index": 233
    },
    {
        "type": "scroll",
        "timestamp": "2024-10-18T03:06:13.497Z",
        "deltaY": 1,
        "yDirection": 1,
        "timestamp_second": 849.466,
        "relative_time": 15.73085185185185,
        "index": 234
    },
    {
        "type": "mousewheel",
        "timestamp": "2024-10-18T03:06:13.875Z",
        "deltaY": 3731,
        "yDirection": 1,
        "duration": 2.596,
        "timestamp_second": 849.844,
        "relative_time": 15.737851851851852,
        "index": 235
    },
    {
        "type": "mousewheel",
        "timestamp": "2024-10-18T03:06:16.621Z",
        "deltaY": 748,
        "yDirection": 2,
        "duration": 0.517,
        "timestamp_second": 852.59,
        "relative_time": 15.788703703703705,
        "index": 236
    },
    {
        "type": "mousewheel",
        "timestamp": "2024-10-18T03:06:17.279Z",
        "deltaY": 119,
        "yDirection": 1,
        "duration": 0.557,
        "timestamp_second": 853.248,
        "relative_time": 15.80088888888889,
        "index": 237
    },
    {
        "type": "mouseMovement",
        "totalMouseMovement": 348.0849730637492,
        "timestamp": "2024-10-18T03:06:18.110Z",
        "duration": 0.036,
        "timestamp_second": 854.079,
        "relative_time": 15.816277777777776,
        "index": 238
    },
    {
        "type": "scroll",
        "timestamp": "2024-10-18T03:06:18.339Z",
        "deltaY": 0,
        "yDirection": 0,
        "timestamp_second": 854.308,
        "relative_time": 15.820518518518517,
        "index": 239
    },
    {
        "type": "idle",
        "timestamp": "2024-10-18T03:06:21.147Z",
        "duration": 4.454,
        "timestamp_second": 857.116,
        "relative_time": 15.872518518518518,
        "index": 240
    },
    {
        "type": "mouseMovement",
        "totalMouseMovement": 471.06900231654436,
        "timestamp": "2024-10-18T03:06:22.600Z",
        "duration": 0.683,
        "timestamp_second": 858.569,
        "relative_time": 15.899425925925925,
        "index": 241
    },
    {
        "type": "click",
        "e": "click",
        "timestamp": "2024-10-18T03:06:23.711Z",
        "target": "TEXTAREA",
        "x": 294,
        "y": 415,
        "timestamp_second": 859.68,
        "relative_time": 15.919999999999998,
        "index": 242
    },
    {
        "type": "paste",
        "timestamp": "2024-10-18T03:06:23.852Z",
        "text": "Weather: Below -15 degrees Celsius in December.",
        "textLength": 47,
        "timestamp_second": 859.821,
        "relative_time": 15.922611111111113,
        "index": 243
    },
    {
        "type": "mouseMovement",
        "totalMouseMovement": 385.54656773138413,
        "timestamp": "2024-10-18T03:06:24.219Z",
        "duration": 0.048,
        "timestamp_second": 860.188,
        "relative_time": 15.929407407407407,
        "index": 244
    },
    {
        "type": "idle",
        "timestamp": "2024-10-18T03:06:27.268Z",
        "duration": 6.192,
        "timestamp_second": 863.237,
        "relative_time": 15.98587037037037,
        "index": 245
    },
    {
        "type": "mouseMovement",
        "totalMouseMovement": 401.85456622196216,
        "timestamp": "2024-10-18T03:06:30.459Z",
        "duration": 0.318,
        "timestamp_second": 866.428,
        "relative_time": 16.044962962962963,
        "index": 246
    },
    {
        "type": "click",
        "e": "click",
        "timestamp": "2024-10-18T03:06:31.387Z",
        "target": "TEXTAREA",
        "x": 300,
        "y": 460,
        "timestamp_second": 867.356,
        "relative_time": 16.062148148148147,
        "index": 247
    },
    {
        "type": "paste",
        "timestamp": "2024-10-18T03:06:31.711Z",
        "text": "Driving: Left-hand drive.",
        "textLength": 25,
        "timestamp_second": 867.68,
        "relative_time": 16.068148148148147,
        "index": 248
    },
    {
        "type": "mouseMovement",
        "totalMouseMovement": 415.13652394922246,
        "timestamp": "2024-10-18T03:06:31.985Z",
        "duration": 0.057,
        "timestamp_second": 867.954,
        "relative_time": 16.07322222222222,
        "index": 249
    },
    {
        "type": "idle",
        "timestamp": "2024-10-18T03:06:35.054Z",
        "duration": 8.425,
        "timestamp_second": 871.023,
        "relative_time": 16.130055555555558,
        "index": 250
    },
    {
        "type": "mouseMovement",
        "totalMouseMovement": 280.7097431889051,
        "timestamp": "2024-10-18T03:06:40.467Z",
        "duration": 0.421,
        "timestamp_second": 876.436,
        "relative_time": 16.2302962962963,
        "index": 251
    },
    {
        "type": "click",
        "e": "click",
        "timestamp": "2024-10-18T03:06:41.389Z",
        "target": "TEXTAREA",
        "x": 425,
        "y": 496,
        "timestamp_second": 877.358,
        "relative_time": 16.24737037037037,
        "index": 252
    },
    {
        "type": "paste",
        "timestamp": "2024-10-18T03:06:41.804Z",
        "text": "Visit local markets.",
        "textLength": 20,
        "timestamp_second": 877.773,
        "relative_time": 16.255055555555558,
        "index": 253
    },
    {
        "type": "mouseMovement",
        "totalMouseMovement": 758.8907559031722,
        "timestamp": "2024-10-18T03:06:42.148Z",
        "duration": 3.182,
        "timestamp_second": 878.117,
        "relative_time": 16.261425925925927,
        "index": 254
    },
    {
        "type": "click",
        "e": "click",
        "timestamp": "2024-10-18T03:06:45.841Z",
        "target": "TEXTAREA",
        "x": 302,
        "y": 569,
        "timestamp_second": 881.81,
        "relative_time": 16.329814814814814,
        "index": 255
    },
    {
        "type": "paste",
        "timestamp": "2024-10-18T03:06:45.884Z",
        "text": "Tap water is high-quality; carry a refillable bottle.",
        "textLength": 53,
        "timestamp_second": 881.853,
        "relative_time": 16.33061111111111,
        "index": 256
    },
    {
        "type": "mousewheel",
        "timestamp": "2024-10-18T03:06:46.446Z",
        "deltaY": 440,
        "yDirection": 1,
        "duration": 1.093,
        "timestamp_second": 882.415,
        "relative_time": 16.341018518518517,
        "index": 257
    },
    {
        "type": "scroll",
        "timestamp": "2024-10-18T03:06:48.043Z",
        "deltaY": 0,
        "yDirection": 0,
        "timestamp_second": 884.012,
        "relative_time": 16.370592592592594,
        "index": 258
    },
    {
        "type": "mousewheel",
        "timestamp": "2024-10-18T03:06:48.394Z",
        "deltaY": 187,
        "yDirection": 2,
        "duration": 0.265,
        "timestamp_second": 884.363,
        "relative_time": 16.377092592592593,
        "index": 259
    },
    {
        "type": "mouseMovement",
        "totalMouseMovement": 445.1318943682563,
        "timestamp": "2024-10-18T03:06:48.977Z",
        "duration": 0.06,
        "timestamp_second": 884.946,
        "relative_time": 16.38788888888889,
        "index": 260
    },
    {
        "type": "scroll",
        "timestamp": "2024-10-18T03:06:49.171Z",
        "deltaY": 1,
        "yDirection": 2,
        "timestamp_second": 885.14,
        "relative_time": 16.39148148148148,
        "index": 261
    },
    {
        "type": "idle",
        "timestamp": "2024-10-18T03:06:52.038Z",
        "duration": 6.851,
        "timestamp_second": 888.007,
        "relative_time": 16.444574074074072,
        "index": 262
    },
    {
        "type": "mouseMovement",
        "totalMouseMovement": 327.84802016356116,
        "timestamp": "2024-10-18T03:06:55.888Z",
        "duration": 0.166,
        "timestamp_second": 891.857,
        "relative_time": 16.51587037037037,
        "index": 263
    },
    {
        "type": "mousewheel",
        "timestamp": "2024-10-18T03:06:56.487Z",
        "deltaY": 89,
        "yDirection": 1,
        "duration": 0.482,
        "timestamp_second": 892.456,
        "relative_time": 16.526962962962962,
        "index": 264
    },
    {
        "type": "scroll",
        "timestamp": "2024-10-18T03:06:57.473Z",
        "deltaY": 2,
        "yDirection": 1,
        "timestamp_second": 893.442,
        "relative_time": 16.545222222222222,
        "index": 265
    },
    {
        "type": "mousewheel",
        "timestamp": "2024-10-18T03:06:57.536Z",
        "deltaY": 84,
        "yDirection": 1,
        "duration": 1.473,
        "timestamp_second": 893.505,
        "relative_time": 16.546388888888888,
        "index": 266
    },
    {
        "type": "scroll",
        "timestamp": "2024-10-18T03:06:59.520Z",
        "deltaY": 0,
        "yDirection": 0,
        "timestamp_second": 895.489,
        "relative_time": 16.58312962962963,
        "index": 267
    },
    {
        "type": "mousewheel",
        "timestamp": "2024-10-18T03:07:01.083Z",
        "deltaY": 82,
        "yDirection": 1,
        "duration": 0.433,
        "timestamp_second": 897.052,
        "relative_time": 16.612074074074073,
        "index": 268
    },
    {
        "type": "mouseMovement",
        "totalMouseMovement": 431.03700617483264,
        "timestamp": "2024-10-18T03:07:01.852Z",
        "duration": 0.166,
        "timestamp_second": 897.821,
        "relative_time": 16.626314814814815,
        "index": 269
    },
    {
        "type": "scroll",
        "timestamp": "2024-10-18T03:07:02.018Z",
        "deltaY": 1,
        "yDirection": 1,
        "timestamp_second": 897.987,
        "relative_time": 16.629388888888887,
        "index": 270
    },
    {
        "type": "mouseMovement",
        "totalMouseMovement": 505.66106334947835,
        "timestamp": "2024-10-18T03:07:02.033Z",
        "duration": 4.185,
        "timestamp_second": 898.002,
        "relative_time": 16.629666666666665,
        "index": 271
    }
]