[
    {
        "type": "click",
        "e": "click",
        "timestamp": "2024-10-19T01:37:40.287Z",
        "target": "BUTTON",
        "x": 727,
        "y": 16,
        "timestamp_second": 0.0,
        "relative_time": 0.0,
        "index": 0
    },
    {
        "type": "mouseMovement",
        "totalMouseMovement": 173.88947287730116,
        "timestamp": "2024-10-19T01:37:40.514Z",
        "duration": 0.171,
        "timestamp_second": 0.227,
        "relative_time": 0.004203703703703703,
        "index": 1
    },
    {
        "type": "idle",
        "timestamp": "2024-10-19T01:37:43.686Z",
        "duration": 21.783,
        "timestamp_second": 3.399,
        "relative_time": 0.06294444444444444,
        "index": 2
    },
    {
        "type": "mouseMovement",
        "totalMouseMovement": 123.33981154971389,
        "timestamp": "2024-10-19T01:38:02.468Z",
        "duration": 1.552,
        "timestamp_second": 22.181,
        "relative_time": 0.4107592592592592,
        "index": 3
    },
    {
        "type": "highlight",
        "timestamp": "2024-10-19T01:38:04.181Z",
        "highlightedText": "list 6 interesting spots in Copenhagen as the potential destinations, as well as the reason for choosing them, the admission prices, and the opening days, and list 6 important “travel tips” about Copenhagen.",
        "highlightedTextLength": 207,
        "timestamp_second": 23.894,
        "relative_time": 0.4424814814814815,
        "index": 4
    },
    {
        "type": "click",
        "e": "click",
        "timestamp": "2024-10-19T01:38:04.183Z",
        "target": "TEXTAREA",
        "x": 191,
        "y": 370,
        "timestamp_second": 23.896,
        "relative_time": 0.4425185185185186,
        "index": 5
    },
    {
        "type": "mouseMovement",
        "totalMouseMovement": 137.11584540217973,
        "timestamp": "2024-10-19T01:38:04.187Z",
        "duration": 1.262,
        "timestamp_second": 23.9,
        "relative_time": 0.4425925925925926,
        "index": 6
    },
    {
        "type": "copy",
        "timestamp": "2024-10-19T01:38:05.465Z",
        "text": "list 6 interesting spots in Copenhagen as the potential destinations, as well as the reason for choosing them, the admission prices, and the opening days, and list 6 important “travel tips” about Copenhagen.",
        "textLength": 207,
        "timestamp_second": 25.178,
        "relative_time": 0.4662592592592593,
        "index": 7
    },
    {
        "type": "mouseMovement",
        "totalMouseMovement": 457.4952714110823,
        "timestamp": "2024-10-19T01:38:05.685Z",
        "duration": 0.414,
        "timestamp_second": 25.398,
        "relative_time": 0.4703333333333334,
        "index": 8
    },
    {
        "type": "idle",
        "timestamp": "2024-10-19T01:38:09.101Z",
        "duration": 161.465,
        "timestamp_second": 28.814,
        "relative_time": 0.5335925925925926,
        "index": 9
    },
    {
        "type": "mouseMovement",
        "totalMouseMovement": 355.6247822499254,
        "timestamp": "2024-10-19T01:40:47.564Z",
        "duration": 2.064,
        "timestamp_second": 187.277,
        "relative_time": 3.4680925925925923,
        "index": 10
    },
    {
        "type": "highlight",
        "timestamp": "2024-10-19T01:40:49.923Z",
        "highlightedText": "Location 1:\n\tlocation: UCLA\n\treason: it's a famous university\n\tprice: free\n\topening days: all days\nLocation 2:",
        "highlightedTextLength": 110,
        "timestamp_second": 189.636,
        "relative_time": 3.5117777777777777,
        "index": 11
    },
    {
        "type": "click",
        "e": "click",
        "timestamp": "2024-10-19T01:40:49.925Z",
        "target": "TEXTAREA",
        "x": 311,
        "y": 644,
        "timestamp_second": 189.638,
        "relative_time": 3.511814814814815,
        "index": 12
    },
    {
        "type": "mouseMovement",
        "totalMouseMovement": 429.92817421283326,
        "timestamp": "2024-10-19T01:40:50.225Z",
        "duration": 0.112,
        "timestamp_second": 189.938,
        "relative_time": 3.51737037037037,
        "index": 13
    },
    {
        "type": "copy",
        "timestamp": "2024-10-19T01:40:50.578Z",
        "text": "Location 1:\n\tlocation: UCLA\n\treason: it's a famous university\n\tprice: free\n\topening days: all days\nLocation 2:",
        "textLength": 110,
        "timestamp_second": 190.291,
        "relative_time": 3.5239074074074077,
        "index": 14
    },
    {
        "type": "idle",
        "timestamp": "2024-10-19T01:40:53.339Z",
        "duration": 11.728000000000002,
        "timestamp_second": 193.052,
        "relative_time": 3.575037037037037,
        "index": 15
    },
    {
        "type": "mousewheel",
        "timestamp": "2024-10-19T01:41:02.065Z",
        "deltaY": 186,
        "yDirection": 1,
        "duration": 0.324,
        "timestamp_second": 201.778,
        "relative_time": 3.7366296296296295,
        "index": 16
    },
    {
        "type": "scroll",
        "timestamp": "2024-10-19T01:41:02.890Z",
        "deltaY": 1,
        "yDirection": 1,
        "timestamp_second": 202.603,
        "relative_time": 3.7519074074074075,
        "index": 17
    },
    {
        "type": "mousewheel",
        "timestamp": "2024-10-19T01:41:03.129Z",
        "deltaY": 91,
        "yDirection": 2,
        "duration": 0.369,
        "timestamp_second": 202.842,
        "relative_time": 3.756333333333334,
        "index": 18
    },
    {
        "type": "scroll",
        "timestamp": "2024-10-19T01:41:03.999Z",
        "deltaY": 1,
        "yDirection": 2,
        "timestamp_second": 203.712,
        "relative_time": 3.772444444444444,
        "index": 19
    },
    {
        "type": "idle",
        "timestamp": "2024-10-19T01:41:06.499Z",
        "duration": 119.95100000000001,
        "timestamp_second": 206.212,
        "relative_time": 3.8187407407407408,
        "index": 20
    },
    {
        "type": "mousewheel",
        "timestamp": "2024-10-19T01:43:03.449Z",
        "deltaY": 350,
        "yDirection": 1,
        "duration": 0.276,
        "timestamp_second": 323.162,
        "relative_time": 5.984481481481481,
        "index": 21
    },
    {
        "type": "scroll",
        "timestamp": "2024-10-19T01:43:04.227Z",
        "deltaY": 2,
        "yDirection": 1,
        "timestamp_second": 323.94,
        "relative_time": 5.998888888888889,
        "index": 22
    },
    {
        "type": "mousewheel",
        "timestamp": "2024-10-19T01:43:04.525Z",
        "deltaY": 364,
        "yDirection": 1,
        "duration": 0.333,
        "timestamp_second": 324.238,
        "relative_time": 6.004407407407408,
        "index": 23
    },
    {
        "type": "mouseMovement",
        "totalMouseMovement": 90.3344815800483,
        "timestamp": "2024-10-19T01:43:05.079Z",
        "duration": 0.213,
        "timestamp_second": 324.792,
        "relative_time": 6.014666666666666,
        "index": 24
    },
    {
        "type": "scroll",
        "timestamp": "2024-10-19T01:43:05.359Z",
        "deltaY": 1,
        "yDirection": 1,
        "timestamp_second": 325.072,
        "relative_time": 6.019851851851852,
        "index": 25
    },
    {
        "type": "highlight",
        "timestamp": "2024-10-19T01:43:05.388Z",
        "highlightedText": "Location 1:\n\tlocation: UCLA\n\treason: it's a famous university\n\tprice: free\n\topening days: all days\nLocation 2:",
        "highlightedTextLength": 110,
        "timestamp_second": 325.101,
        "relative_time": 6.020388888888889,
        "index": 26
    },
    {
        "type": "click",
        "e": "click",
        "timestamp": "2024-10-19T01:43:05.388Z",
        "target": "P",
        "x": 496,
        "y": 263,
        "timestamp_second": 325.101,
        "relative_time": 6.020388888888889,
        "index": 27
    },
    {
        "type": "mouseMovement",
        "totalMouseMovement": 208.74578425202708,
        "timestamp": "2024-10-19T01:43:05.683Z",
        "duration": 0.126,
        "timestamp_second": 325.396,
        "relative_time": 6.0258518518518525,
        "index": 28
    },
    {
        "type": "mousewheel",
        "timestamp": "2024-10-19T01:43:06.001Z",
        "deltaY": 523,
        "yDirection": 1,
        "duration": 1.95,
        "timestamp_second": 325.714,
        "relative_time": 6.031740740740741,
        "index": 29
    },
    {
        "type": "scroll",
        "timestamp": "2024-10-19T01:43:08.452Z",
        "deltaY": 1,
        "yDirection": 1,
        "timestamp_second": 328.165,
        "relative_time": 6.07712962962963,
        "index": 30
    },
    {
        "type": "mouseMovement",
        "totalMouseMovement": 243.39694091522688,
        "timestamp": "2024-10-19T01:43:08.834Z",
        "duration": 0.091,
        "timestamp_second": 328.547,
        "relative_time": 6.084203703703704,
        "index": 31
    },
    {
        "type": "idle",
        "timestamp": "2024-10-19T01:43:11.927Z",
        "duration": 10.116,
        "timestamp_second": 331.64,
        "relative_time": 6.141481481481481,
        "index": 32
    },
    {
        "type": "keypress",
        "timestamp": "2024-10-19T01:43:19.041Z",
        "duration": 0.314,
        "key_list": "goo",
        "keyCode_list": [
            103,
            111,
            111
        ],
        "target": "BODY",
        "key_count": 3,
        "timestamp_second": 338.754,
        "relative_time": 6.273222222222223,
        "index": 33
    },
    {
        "type": "idle",
        "timestamp": "2024-10-19T01:43:22.356Z",
        "duration": 13.208,
        "timestamp_second": 342.069,
        "relative_time": 6.334611111111112,
        "index": 34
    },
    {
        "type": "mouseMovement",
        "totalMouseMovement": 2.0,
        "timestamp": "2024-10-19T01:43:32.563Z",
        "duration": 0.042,
        "timestamp_second": 352.276,
        "relative_time": 6.523629629629629,
        "index": 35
    },
    {
        "type": "click",
        "e": "click",
        "timestamp": "2024-10-19T01:43:32.737Z",
        "target": "TEXTAREA",
        "x": 307,
        "y": 151,
        "timestamp_second": 352.45,
        "relative_time": 6.526851851851852,
        "index": 36
    },
    {
        "type": "paste",
        "timestamp": "2024-10-19T01:43:33.054Z",
        "text": "Amarienborg",
        "textLength": 11,
        "timestamp_second": 352.767,
        "relative_time": 6.532722222222222,
        "index": 37
    },
    {
        "type": "mouseMovement",
        "totalMouseMovement": 455.7971830756069,
        "timestamp": "2024-10-19T01:43:33.074Z",
        "duration": 0.406,
        "timestamp_second": 352.787,
        "relative_time": 6.533092592592592,
        "index": 38
    },
    {
        "type": "idle",
        "timestamp": "2024-10-19T01:43:36.482Z",
        "duration": 5.725,
        "timestamp_second": 356.195,
        "relative_time": 6.596203703703704,
        "index": 39
    },
    {
        "type": "mouseMovement",
        "totalMouseMovement": 36.0258093446173,
        "timestamp": "2024-10-19T01:43:39.205Z",
        "duration": 0.157,
        "timestamp_second": 358.918,
        "relative_time": 6.64662962962963,
        "index": 40
    },
    {
        "type": "click",
        "e": "click",
        "timestamp": "2024-10-19T01:43:39.435Z",
        "target": "TEXTAREA",
        "x": 277,
        "y": 188,
        "timestamp_second": 359.148,
        "relative_time": 6.65088888888889,
        "index": 41
    },
    {
        "type": "mouseMovement",
        "totalMouseMovement": 3.162277660168911,
        "timestamp": "2024-10-19T01:43:39.648Z",
        "duration": 0.011,
        "timestamp_second": 359.361,
        "relative_time": 6.654833333333333,
        "index": 42
    },
    {
        "type": "paste",
        "timestamp": "2024-10-19T01:43:39.667Z",
        "text": "It's the home of the Danish royal family and you can witness the change of guard at 12:00.",
        "textLength": 90,
        "timestamp_second": 359.38,
        "relative_time": 6.655185185185185,
        "index": 43
    },
    {
        "type": "mouseMovement",
        "totalMouseMovement": 460.26074135018825,
        "timestamp": "2024-10-19T01:43:39.670Z",
        "duration": 0.075,
        "timestamp_second": 359.383,
        "relative_time": 6.655240740740741,
        "index": 44
    },
    {
        "type": "click",
        "e": "click",
        "timestamp": "2024-10-19T01:43:43.250Z",
        "target": "TEXTAREA",
        "x": 272,
        "y": 268,
        "timestamp_second": 362.963,
        "relative_time": 6.721537037037037,
        "index": 45
    },
    {
        "type": "click",
        "e": "click",
        "timestamp": "2024-10-19T01:43:43.252Z",
        "target": "TEXTAREA",
        "x": 272,
        "y": 268,
        "timestamp_second": 362.965,
        "relative_time": 6.721574074074074,
        "index": 46
    },
    {
        "type": "paste",
        "timestamp": "2024-10-19T01:43:43.676Z",
        "text": "$1.25",
        "textLength": 5,
        "timestamp_second": 363.389,
        "relative_time": 6.729425925925926,
        "index": 47
    },
    {
        "type": "mouseMovement",
        "totalMouseMovement": 452.01441995239475,
        "timestamp": "2024-10-19T01:43:43.713Z",
        "duration": 0.087,
        "timestamp_second": 363.426,
        "relative_time": 6.7301111111111105,
        "index": 48
    },
    {
        "type": "click",
        "e": "click",
        "timestamp": "2024-10-19T01:43:46.454Z",
        "target": "TEXTAREA",
        "x": 359,
        "y": 310,
        "timestamp_second": 366.167,
        "relative_time": 6.78087037037037,
        "index": 49
    },
    {
        "type": "click",
        "e": "click",
        "timestamp": "2024-10-19T01:43:46.457Z",
        "target": "TEXTAREA",
        "x": 359,
        "y": 310,
        "timestamp_second": 366.17,
        "relative_time": 6.780925925925926,
        "index": 50
    },
    {
        "type": "paste",
        "timestamp": "2024-10-19T01:43:46.751Z",
        "text": "All week",
        "textLength": 8,
        "timestamp_second": 366.464,
        "relative_time": 6.786370370370371,
        "index": 51
    },
    {
        "type": "mouseMovement",
        "totalMouseMovement": 364.47943651690184,
        "timestamp": "2024-10-19T01:43:46.904Z",
        "duration": 0.23,
        "timestamp_second": 366.617,
        "relative_time": 6.789203703703704,
        "index": 52
    },
    {
        "type": "mousewheel",
        "timestamp": "2024-10-19T01:43:47.300Z",
        "deltaY": 175,
        "yDirection": 1,
        "duration": 0.308,
        "timestamp_second": 367.013,
        "relative_time": 6.796537037037037,
        "index": 53
    },
    {
        "type": "mouseMovement",
        "totalMouseMovement": 299.345176712186,
        "timestamp": "2024-10-19T01:43:47.638Z",
        "duration": 0.058,
        "timestamp_second": 367.351,
        "relative_time": 6.802796296296296,
        "index": 54
    },
    {
        "type": "scroll",
        "timestamp": "2024-10-19T01:43:48.108Z",
        "deltaY": 3,
        "yDirection": 1,
        "timestamp_second": 367.821,
        "relative_time": 6.8115000000000006,
        "index": 55
    },
    {
        "type": "click",
        "e": "click",
        "timestamp": "2024-10-19T01:43:51.084Z",
        "target": "TEXTAREA",
        "x": 388,
        "y": 288,
        "timestamp_second": 370.797,
        "relative_time": 6.866611111111112,
        "index": 56
    },
    {
        "type": "click",
        "e": "click",
        "timestamp": "2024-10-19T01:43:51.086Z",
        "target": "TEXTAREA",
        "x": 388,
        "y": 288,
        "timestamp_second": 370.799,
        "relative_time": 6.8666481481481485,
        "index": 57
    },
    {
        "type": "paste",
        "timestamp": "2024-10-19T01:43:51.310Z",
        "text": "The Little Mermaid Statue",
        "textLength": 25,
        "timestamp_second": 371.023,
        "relative_time": 6.870796296296297,
        "index": 58
    },
    {
        "type": "mouseMovement",
        "totalMouseMovement": 366.70805535554246,
        "timestamp": "2024-10-19T01:43:51.449Z",
        "duration": 0.093,
        "timestamp_second": 371.162,
        "relative_time": 6.87337037037037,
        "index": 59
    },
    {
        "type": "idle",
        "timestamp": "2024-10-19T01:43:54.543Z",
        "duration": 5.275,
        "timestamp_second": 374.256,
        "relative_time": 6.930666666666665,
        "index": 60
    },
    {
        "type": "mouseMovement",
        "totalMouseMovement": 145.98317298288202,
        "timestamp": "2024-10-19T01:43:56.817Z",
        "duration": 0.217,
        "timestamp_second": 376.53,
        "relative_time": 6.972777777777778,
        "index": 61
    },
    {
        "type": "click",
        "e": "click",
        "timestamp": "2024-10-19T01:43:57.157Z",
        "target": "TEXTAREA",
        "x": 405,
        "y": 321,
        "timestamp_second": 376.87,
        "relative_time": 6.979074074074074,
        "index": 62
    },
    {
        "type": "paste",
        "timestamp": "2024-10-19T01:43:57.365Z",
        "text": "It's a character from Grimm's Fairy Tales and a symbol of Copenhagen.",
        "textLength": 69,
        "timestamp_second": 377.078,
        "relative_time": 6.982925925925926,
        "index": 63
    },
    {
        "type": "mouseMovement",
        "totalMouseMovement": 357.97195859963176,
        "timestamp": "2024-10-19T01:43:57.514Z",
        "duration": 0.07,
        "timestamp_second": 377.227,
        "relative_time": 6.985685185185185,
        "index": 64
    },
    {
        "type": "idle",
        "timestamp": "2024-10-19T01:44:00.585Z",
        "duration": 3.955,
        "timestamp_second": 380.298,
        "relative_time": 7.042555555555556,
        "index": 65
    },
    {
        "type": "mouseMovement",
        "totalMouseMovement": 91.95172144637763,
        "timestamp": "2024-10-19T01:44:01.539Z",
        "duration": 0.19,
        "timestamp_second": 381.252,
        "relative_time": 7.0602222222222215,
        "index": 66
    },
    {
        "type": "click",
        "e": "click",
        "timestamp": "2024-10-19T01:44:01.834Z",
        "target": "TD",
        "x": 438,
        "y": 443,
        "timestamp_second": 381.547,
        "relative_time": 7.065685185185186,
        "index": 67
    },
    {
        "type": "mouseMovement",
        "totalMouseMovement": 24.970609457455794,
        "timestamp": "2024-10-19T01:44:01.862Z",
        "duration": 0.364,
        "timestamp_second": 381.575,
        "relative_time": 7.066203703703704,
        "index": 68
    },
    {
        "type": "click",
        "e": "click",
        "timestamp": "2024-10-19T01:44:02.315Z",
        "target": "TEXTAREA",
        "x": 447,
        "y": 420,
        "timestamp_second": 382.028,
        "relative_time": 7.074592592592594,
        "index": 69
    },
    {
        "type": "paste",
        "timestamp": "2024-10-19T01:44:02.513Z",
        "text": "Free",
        "textLength": 4,
        "timestamp_second": 382.226,
        "relative_time": 7.0782592592592595,
        "index": 70
    },
    {
        "type": "mouseMovement",
        "totalMouseMovement": 322.4675563975652,
        "timestamp": "2024-10-19T01:44:02.550Z",
        "duration": 2.874,
        "timestamp_second": 382.263,
        "relative_time": 7.078944444444445,
        "index": 71
    },
    {
        "type": "click",
        "e": "click",
        "timestamp": "2024-10-19T01:44:05.671Z",
        "target": "TEXTAREA",
        "x": 289,
        "y": 474,
        "timestamp_second": 385.384,
        "relative_time": 7.13674074074074,
        "index": 72
    },
    {
        "type": "paste",
        "timestamp": "2024-10-19T01:44:05.811Z",
        "text": "All week",
        "textLength": 8,
        "timestamp_second": 385.524,
        "relative_time": 7.139333333333334,
        "index": 73
    },
    {
        "type": "mousewheel",
        "timestamp": "2024-10-19T01:44:06.089Z",
        "deltaY": 173,
        "yDirection": 1,
        "duration": 0.302,
        "timestamp_second": 385.802,
        "relative_time": 7.144481481481482,
        "index": 74
    },
    {
        "type": "mouseMovement",
        "totalMouseMovement": 454.1363701431037,
        "timestamp": "2024-10-19T01:44:06.425Z",
        "duration": 0.082,
        "timestamp_second": 386.138,
        "relative_time": 7.150703703703703,
        "index": 75
    },
    {
        "type": "scroll",
        "timestamp": "2024-10-19T01:44:06.893Z",
        "deltaY": 3,
        "yDirection": 1,
        "timestamp_second": 386.606,
        "relative_time": 7.15937037037037,
        "index": 76
    },
    {
        "type": "idle",
        "timestamp": "2024-10-19T01:44:09.507Z",
        "duration": 3.251,
        "timestamp_second": 389.22,
        "relative_time": 7.207777777777778,
        "index": 77
    },
    {
        "type": "mouseMovement",
        "totalMouseMovement": 462.8241098505732,
        "timestamp": "2024-10-19T01:44:09.758Z",
        "duration": 0.37,
        "timestamp_second": 389.471,
        "relative_time": 7.212425925925927,
        "index": 78
    },
    {
        "type": "click",
        "e": "click",
        "timestamp": "2024-10-19T01:44:10.328Z",
        "target": "TEXTAREA",
        "x": 245,
        "y": 598,
        "timestamp_second": 390.041,
        "relative_time": 7.222981481481481,
        "index": 79
    },
    {
        "type": "mouseMovement",
        "totalMouseMovement": 479.59584965125396,
        "timestamp": "2024-10-19T01:44:10.846Z",
        "duration": 0.241,
        "timestamp_second": 390.559,
        "relative_time": 7.2325740740740745,
        "index": 80
    },
    {
        "type": "idle",
        "timestamp": "2024-10-19T01:44:14.089Z",
        "duration": 4.494,
        "timestamp_second": 393.802,
        "relative_time": 7.292629629629629,
        "index": 81
    },
    {
        "type": "click",
        "e": "click",
        "timestamp": "2024-10-19T01:44:15.581Z",
        "target": "TEXTAREA",
        "x": 314,
        "y": 545,
        "timestamp_second": 395.294,
        "relative_time": 7.320259259259259,
        "index": 82
    },
    {
        "type": "paste",
        "timestamp": "2024-10-19T01:44:15.959Z",
        "text": "Around $100 for a dinner",
        "textLength": 24,
        "timestamp_second": 395.672,
        "relative_time": 7.32725925925926,
        "index": 83
    },
    {
        "type": "mouseMovement",
        "totalMouseMovement": 378.885832289232,
        "timestamp": "2024-10-19T01:44:16.087Z",
        "duration": 0.084,
        "timestamp_second": 395.8,
        "relative_time": 7.329629629629631,
        "index": 84
    },
    {
        "type": "idle",
        "timestamp": "2024-10-19T01:44:19.172Z",
        "duration": 3.731,
        "timestamp_second": 398.885,
        "relative_time": 7.38675925925926,
        "index": 85
    },
    {
        "type": "mouseMovement",
        "totalMouseMovement": 222.0980019648523,
        "timestamp": "2024-10-19T01:44:19.902Z",
        "duration": 0.239,
        "timestamp_second": 399.615,
        "relative_time": 7.400277777777778,
        "index": 86
    },
    {
        "type": "click",
        "e": "click",
        "timestamp": "2024-10-19T01:44:20.263Z",
        "target": "TEXTAREA",
        "x": 262,
        "y": 502,
        "timestamp_second": 399.976,
        "relative_time": 7.406962962962963,
        "index": 87
    },
    {
        "type": "paste",
        "timestamp": "2024-10-19T01:44:20.445Z",
        "text": "It's a world-famous restaurant known for its reinterpretation of the Nordic Cuisine.",
        "textLength": 84,
        "timestamp_second": 400.158,
        "relative_time": 7.410333333333334,
        "index": 88
    },
    {
        "type": "mouseMovement",
        "totalMouseMovement": 433.9584908753677,
        "timestamp": "2024-10-19T01:44:20.481Z",
        "duration": 0.072,
        "timestamp_second": 400.194,
        "relative_time": 7.411000000000001,
        "index": 89
    },
    {
        "type": "click",
        "e": "click",
        "timestamp": "2024-10-19T01:44:24.010Z",
        "target": "TEXTAREA",
        "x": 444,
        "y": 432,
        "timestamp_second": 403.723,
        "relative_time": 7.476351851851852,
        "index": 90
    },
    {
        "type": "click",
        "e": "click",
        "timestamp": "2024-10-19T01:44:24.011Z",
        "target": "TEXTAREA",
        "x": 444,
        "y": 432,
        "timestamp_second": 403.724,
        "relative_time": 7.476370370370371,
        "index": 91
    },
    {
        "type": "paste",
        "timestamp": "2024-10-19T01:44:24.275Z",
        "text": "Noma",
        "textLength": 4,
        "timestamp_second": 403.988,
        "relative_time": 7.48125925925926,
        "index": 92
    },
    {
        "type": "mousewheel",
        "timestamp": "2024-10-19T01:44:24.526Z",
        "deltaY": 453,
        "yDirection": 1,
        "duration": 0.885,
        "timestamp_second": 404.239,
        "relative_time": 7.485907407407407,
        "index": 93
    },
    {
        "type": "mouseMovement",
        "totalMouseMovement": 236.15540077739388,
        "timestamp": "2024-10-19T01:44:25.456Z",
        "duration": 0.072,
        "timestamp_second": 405.169,
        "relative_time": 7.503129629629629,
        "index": 94
    },
    {
        "type": "scroll",
        "timestamp": "2024-10-19T01:44:25.913Z",
        "deltaY": 2,
        "yDirection": 1,
        "timestamp_second": 405.626,
        "relative_time": 7.511592592592592,
        "index": 95
    },
    {
        "type": "idle",
        "timestamp": "2024-10-19T01:44:28.529Z",
        "duration": 5.927,
        "timestamp_second": 408.242,
        "relative_time": 7.560037037037038,
        "index": 96
    },
    {
        "type": "mouseMovement",
        "totalMouseMovement": 95.22137002718227,
        "timestamp": "2024-10-19T01:44:31.455Z",
        "duration": 0.207,
        "timestamp_second": 411.168,
        "relative_time": 7.614222222222223,
        "index": 97
    },
    {
        "type": "click",
        "e": "click",
        "timestamp": "2024-10-19T01:44:31.781Z",
        "target": "TEXTAREA",
        "x": 430,
        "y": 300,
        "timestamp_second": 411.494,
        "relative_time": 7.62025925925926,
        "index": 98
    },
    {
        "type": "paste",
        "timestamp": "2024-10-19T01:44:32.001Z",
        "text": "Christiansborg Palace",
        "textLength": 21,
        "timestamp_second": 411.714,
        "relative_time": 7.6243333333333325,
        "index": 99
    },
    {
        "type": "mouseMovement",
        "totalMouseMovement": 390.98728644152834,
        "timestamp": "2024-10-19T01:44:32.058Z",
        "duration": 3.612,
        "timestamp_second": 411.771,
        "relative_time": 7.625388888888889,
        "index": 100
    },
    {
        "type": "click",
        "e": "click",
        "timestamp": "2024-10-19T01:44:35.775Z",
        "target": "TEXTAREA",
        "x": 354,
        "y": 348,
        "timestamp_second": 415.488,
        "relative_time": 7.694222222222222,
        "index": 101
    },
    {
        "type": "paste",
        "timestamp": "2024-10-19T01:44:35.983Z",
        "text": "It's one of the most significant landmarks in Copenhagen, both historically and politically.",
        "textLength": 92,
        "timestamp_second": 415.696,
        "relative_time": 7.698074074074075,
        "index": 102
    },
    {
        "type": "mouseMovement",
        "totalMouseMovement": 454.0827274416806,
        "timestamp": "2024-10-19T01:44:36.125Z",
        "duration": 3.636,
        "timestamp_second": 415.838,
        "relative_time": 7.700703703703704,
        "index": 103
    },
    {
        "type": "click",
        "e": "click",
        "timestamp": "2024-10-19T01:44:39.858Z",
        "target": "TEXTAREA",
        "x": 366,
        "y": 440,
        "timestamp_second": 419.571,
        "relative_time": 7.7698333333333345,
        "index": 104
    },
    {
        "type": "paste",
        "timestamp": "2024-10-19T01:44:40.075Z",
        "text": "Free",
        "textLength": 4,
        "timestamp_second": 419.788,
        "relative_time": 7.773851851851853,
        "index": 105
    },
    {
        "type": "mouseMovement",
        "totalMouseMovement": 357.1267228333745,
        "timestamp": "2024-10-19T01:44:40.124Z",
        "duration": 0.071,
        "timestamp_second": 419.837,
        "relative_time": 7.774759259259259,
        "index": 106
    },
    {
        "type": "idle",
        "timestamp": "2024-10-19T01:44:43.196Z",
        "duration": 4.227,
        "timestamp_second": 422.909,
        "relative_time": 7.8316481481481475,
        "index": 107
    },
    {
        "type": "click",
        "e": "click",
        "timestamp": "2024-10-19T01:44:44.422Z",
        "target": "TEXTAREA",
        "x": 445,
        "y": 469,
        "timestamp_second": 424.135,
        "relative_time": 7.854351851851852,
        "index": 108
    },
    {
        "type": "click",
        "e": "click",
        "timestamp": "2024-10-19T01:44:44.425Z",
        "target": "TEXTAREA",
        "x": 445,
        "y": 469,
        "timestamp_second": 424.138,
        "relative_time": 7.8544074074074075,
        "index": 109
    },
    {
        "type": "paste",
        "timestamp": "2024-10-19T01:44:44.773Z",
        "text": "Tuesday to Sunday",
        "textLength": 17,
        "timestamp_second": 424.486,
        "relative_time": 7.860851851851852,
        "index": 110
    },
    {
        "type": "mousewheel",
        "timestamp": "2024-10-19T01:44:45.031Z",
        "deltaY": 373,
        "yDirection": 1,
        "duration": 0.672,
        "timestamp_second": 424.744,
        "relative_time": 7.86562962962963,
        "index": 111
    },
    {
        "type": "mouseMovement",
        "totalMouseMovement": 269.34307212146814,
        "timestamp": "2024-10-19T01:44:45.886Z",
        "duration": 0.092,
        "timestamp_second": 425.599,
        "relative_time": 7.881462962962963,
        "index": 112
    },
    {
        "type": "scroll",
        "timestamp": "2024-10-19T01:44:46.205Z",
        "deltaY": 2,
        "yDirection": 1,
        "timestamp_second": 425.918,
        "relative_time": 7.887370370370371,
        "index": 113
    },
    {
        "type": "click",
        "e": "click",
        "timestamp": "2024-10-19T01:44:49.404Z",
        "target": "TEXTAREA",
        "x": 279,
        "y": 260,
        "timestamp_second": 429.117,
        "relative_time": 7.946611111111111,
        "index": 114
    },
    {
        "type": "click",
        "e": "click",
        "timestamp": "2024-10-19T01:44:49.407Z",
        "target": "TEXTAREA",
        "x": 279,
        "y": 260,
        "timestamp_second": 429.12,
        "relative_time": 7.946666666666667,
        "index": 115
    },
    {
        "type": "paste",
        "timestamp": "2024-10-19T01:44:49.634Z",
        "text": "Nyhavn",
        "textLength": 6,
        "timestamp_second": 429.347,
        "relative_time": 7.950870370370371,
        "index": 116
    },
    {
        "type": "mouseMovement",
        "totalMouseMovement": 466.92211626870994,
        "timestamp": "2024-10-19T01:44:49.809Z",
        "duration": 0.086,
        "timestamp_second": 429.522,
        "relative_time": 7.954111111111111,
        "index": 117
    },
    {
        "type": "idle",
        "timestamp": "2024-10-19T01:44:52.895Z",
        "duration": 6.035,
        "timestamp_second": 432.608,
        "relative_time": 8.01125925925926,
        "index": 118
    },
    {
        "type": "idle",
        "timestamp": "2024-10-19T01:44:55.930Z",
        "duration": 4.234999999999999,
        "timestamp_second": 435.643,
        "relative_time": 8.067462962962962,
        "index": 119
    },
    {
        "type": "mouseMovement",
        "totalMouseMovement": 91.6935217131504,
        "timestamp": "2024-10-19T01:44:57.163Z",
        "duration": 0.239,
        "timestamp_second": 436.876,
        "relative_time": 8.090296296296295,
        "index": 120
    },
    {
        "type": "click",
        "e": "click",
        "timestamp": "2024-10-19T01:44:57.489Z",
        "target": "TEXTAREA",
        "x": 349,
        "y": 306,
        "timestamp_second": 437.202,
        "relative_time": 8.096333333333334,
        "index": 121
    },
    {
        "type": "paste",
        "timestamp": "2024-10-19T01:44:57.675Z",
        "text": "It's one of Copenhagen's most iconic and picturesque areas, known for its colorful buildings, historic boats, and vibrant atmosphere.",
        "textLength": 133,
        "timestamp_second": 437.388,
        "relative_time": 8.099777777777778,
        "index": 122
    },
    {
        "type": "mouseMovement",
        "totalMouseMovement": 559.8910642045666,
        "timestamp": "2024-10-19T01:44:57.708Z",
        "duration": 0.557,
        "timestamp_second": 437.421,
        "relative_time": 8.100388888888888,
        "index": 123
    },
    {
        "type": "idle",
        "timestamp": "2024-10-19T01:45:01.267Z",
        "duration": 5.481999999999999,
        "timestamp_second": 440.98,
        "relative_time": 8.166296296296297,
        "index": 124
    },
    {
        "type": "paste",
        "timestamp": "2024-10-19T01:45:03.747Z",
        "text": "Free",
        "textLength": 4,
        "timestamp_second": 443.46,
        "relative_time": 8.212222222222222,
        "index": 125
    },
    {
        "type": "mouseMovement",
        "totalMouseMovement": 134.30490390214618,
        "timestamp": "2024-10-19T01:45:04.761Z",
        "duration": 0.358,
        "timestamp_second": 444.474,
        "relative_time": 8.231,
        "index": 126
    },
    {
        "type": "click",
        "e": "click",
        "timestamp": "2024-10-19T01:45:06.142Z",
        "target": "TEXTAREA",
        "x": 325,
        "y": 406,
        "timestamp_second": 445.855,
        "relative_time": 8.256574074074074,
        "index": 127
    },
    {
        "type": "mouseMovement",
        "totalMouseMovement": 459.14380869988963,
        "timestamp": "2024-10-19T01:45:06.822Z",
        "duration": 0.53,
        "timestamp_second": 446.535,
        "relative_time": 8.269166666666667,
        "index": 128
    },
    {
        "type": "click",
        "e": "click",
        "timestamp": "2024-10-19T01:45:07.531Z",
        "target": "TD",
        "x": 266,
        "y": 673,
        "timestamp_second": 447.244,
        "relative_time": 8.282296296296296,
        "index": 129
    },
    {
        "type": "mouseMovement",
        "totalMouseMovement": 18.803263984958903,
        "timestamp": "2024-10-19T01:45:07.808Z",
        "duration": 0.078,
        "timestamp_second": 447.521,
        "relative_time": 8.287425925925925,
        "index": 130
    },
    {
        "type": "click",
        "e": "click",
        "timestamp": "2024-10-19T01:45:08.099Z",
        "target": "TEXTAREA",
        "x": 258,
        "y": 692,
        "timestamp_second": 447.812,
        "relative_time": 8.292814814814815,
        "index": 131
    },
    {
        "type": "mouseMovement",
        "totalMouseMovement": 756.8424841107771,
        "timestamp": "2024-10-19T01:45:08.409Z",
        "duration": 3.932,
        "timestamp_second": 448.122,
        "relative_time": 8.298555555555556,
        "index": 132
    },
    {
        "type": "click",
        "e": "click",
        "timestamp": "2024-10-19T01:45:12.439Z",
        "target": "TEXTAREA",
        "x": 286,
        "y": 442,
        "timestamp_second": 452.152,
        "relative_time": 8.373185185185186,
        "index": 133
    },
    {
        "type": "paste",
        "timestamp": "2024-10-19T01:45:12.775Z",
        "text": "All week",
        "textLength": 8,
        "timestamp_second": 452.488,
        "relative_time": 8.379407407407408,
        "index": 134
    },
    {
        "type": "mouseMovement",
        "totalMouseMovement": 536.2205771959489,
        "timestamp": "2024-10-19T01:45:12.799Z",
        "duration": 3.149,
        "timestamp_second": 452.512,
        "relative_time": 8.379851851851852,
        "index": 135
    },
    {
        "type": "click",
        "e": "click",
        "timestamp": "2024-10-19T01:45:16.142Z",
        "target": "TEXTAREA",
        "x": 314,
        "y": 605,
        "timestamp_second": 455.855,
        "relative_time": 8.44175925925926,
        "index": 136
    },
    {
        "type": "paste",
        "timestamp": "2024-10-19T01:45:16.365Z",
        "text": "Tivoli Gardens",
        "textLength": 14,
        "timestamp_second": 456.078,
        "relative_time": 8.44588888888889,
        "index": 137
    },
    {
        "type": "mouseMovement",
        "totalMouseMovement": 557.5329996001747,
        "timestamp": "2024-10-19T01:45:16.433Z",
        "duration": 3.157,
        "timestamp_second": 456.146,
        "relative_time": 8.447148148148148,
        "index": 138
    },
    {
        "type": "click",
        "e": "click",
        "timestamp": "2024-10-19T01:45:19.786Z",
        "target": "TEXTAREA",
        "x": 328,
        "y": 648,
        "timestamp_second": 459.499,
        "relative_time": 8.50924074074074,
        "index": 139
    },
    {
        "type": "paste",
        "timestamp": "2024-10-19T01:45:19.978Z",
        "text": "Known for its enchanting atmosphere, beautiful gardens, and thrilling amusement park rides.",
        "textLength": 91,
        "timestamp_second": 459.691,
        "relative_time": 8.512796296296296,
        "index": 140
    },
    {
        "type": "mouseMovement",
        "totalMouseMovement": 397.8465955172687,
        "timestamp": "2024-10-19T01:45:20.184Z",
        "duration": 0.074,
        "timestamp_second": 459.897,
        "relative_time": 8.51661111111111,
        "index": 141
    },
    {
        "type": "mousewheel",
        "timestamp": "2024-10-19T01:45:22.809Z",
        "deltaY": 151,
        "yDirection": 1,
        "duration": 0.222,
        "timestamp_second": 462.522,
        "relative_time": 8.565222222222223,
        "index": 142
    },
    {
        "type": "scroll",
        "timestamp": "2024-10-19T01:45:23.533Z",
        "deltaY": 1,
        "yDirection": 1,
        "timestamp_second": 463.246,
        "relative_time": 8.57862962962963,
        "index": 143
    },
    {
        "type": "mouseMovement",
        "totalMouseMovement": 50.95857586655984,
        "timestamp": "2024-10-19T01:45:23.708Z",
        "duration": 0.115,
        "timestamp_second": 463.421,
        "relative_time": 8.581870370370371,
        "index": 144
    },
    {
        "type": "click",
        "e": "click",
        "timestamp": "2024-10-19T01:45:24.025Z",
        "target": "TEXTAREA",
        "x": 428,
        "y": 626,
        "timestamp_second": 463.738,
        "relative_time": 8.58774074074074,
        "index": 145
    },
    {
        "type": "paste",
        "timestamp": "2024-10-19T01:45:24.268Z",
        "text": "Monday to Saturday",
        "textLength": 18,
        "timestamp_second": 463.981,
        "relative_time": 8.59224074074074,
        "index": 146
    },
    {
        "type": "mousewheel",
        "timestamp": "2024-10-19T01:45:24.616Z",
        "deltaY": 459,
        "yDirection": 1,
        "duration": 0.691,
        "timestamp_second": 464.329,
        "relative_time": 8.598685185185186,
        "index": 147
    },
    {
        "type": "mouseMovement",
        "totalMouseMovement": 317.82787613700566,
        "timestamp": "2024-10-19T01:45:25.558Z",
        "duration": 0.082,
        "timestamp_second": 465.271,
        "relative_time": 8.616129629629631,
        "index": 148
    },
    {
        "type": "scroll",
        "timestamp": "2024-10-19T01:45:25.808Z",
        "deltaY": 2,
        "yDirection": 1,
        "timestamp_second": 465.521,
        "relative_time": 8.62075925925926,
        "index": 149
    },
    {
        "type": "idle",
        "timestamp": "2024-10-19T01:45:28.641Z",
        "duration": 8.889,
        "timestamp_second": 468.354,
        "relative_time": 8.673222222222222,
        "index": 150
    },
    {
        "type": "click",
        "e": "click",
        "timestamp": "2024-10-19T01:45:34.529Z",
        "target": "TEXTAREA",
        "x": 320,
        "y": 337,
        "timestamp_second": 474.242,
        "relative_time": 8.78225925925926,
        "index": 151
    },
    {
        "type": "click",
        "e": "click",
        "timestamp": "2024-10-19T01:45:34.532Z",
        "target": "TEXTAREA",
        "x": 320,
        "y": 337,
        "timestamp_second": 474.245,
        "relative_time": 8.782314814814814,
        "index": 152
    },
    {
        "type": "paste",
        "timestamp": "2024-10-19T01:45:34.930Z",
        "text": "You can get a Copenhagen Card that covers 80 attractions and public transports with $30. This card can save you a lot of money if you plan to visit many attractions.",
        "textLength": 165,
        "timestamp_second": 474.643,
        "relative_time": 8.789685185185185,
        "index": 153
    },
    {
        "type": "mouseMovement",
        "totalMouseMovement": 434.01693391829394,
        "timestamp": "2024-10-19T01:45:35.025Z",
        "duration": 0.148,
        "timestamp_second": 474.738,
        "relative_time": 8.791444444444444,
        "index": 154
    },
    {
        "type": "idle",
        "timestamp": "2024-10-19T01:45:38.174Z",
        "duration": 6.106999999999999,
        "timestamp_second": 477.887,
        "relative_time": 8.849759259259258,
        "index": 155
    },
    {
        "type": "mouseMovement",
        "totalMouseMovement": 85.42951688968606,
        "timestamp": "2024-10-19T01:45:41.280Z",
        "duration": 0.206,
        "timestamp_second": 480.993,
        "relative_time": 8.907277777777779,
        "index": 156
    },
    {
        "type": "click",
        "e": "click",
        "timestamp": "2024-10-19T01:45:41.608Z",
        "target": "TEXTAREA",
        "x": 315,
        "y": 442,
        "timestamp_second": 481.321,
        "relative_time": 8.913351851851854,
        "index": 157
    },
    {
        "type": "paste",
        "timestamp": "2024-10-19T01:45:41.899Z",
        "text": "The tip rate in Copenhagen is over 50%. This might be higher than what you're used to, but it's a common practice in Copenhagen.",
        "textLength": 128,
        "timestamp_second": 481.612,
        "relative_time": 8.918740740740741,
        "index": 158
    },
    {
        "type": "mouseMovement",
        "totalMouseMovement": 400.1645551173169,
        "timestamp": "2024-10-19T01:45:41.959Z",
        "duration": 0.094,
        "timestamp_second": 481.672,
        "relative_time": 8.919851851851853,
        "index": 159
    },
    {
        "type": "idle",
        "timestamp": "2024-10-19T01:45:45.053Z",
        "duration": 4.99,
        "timestamp_second": 484.766,
        "relative_time": 8.977148148148148,
        "index": 160
    },
    {
        "type": "mouseMovement",
        "totalMouseMovement": 36.95933787431932,
        "timestamp": "2024-10-19T01:45:47.043Z",
        "duration": 0.134,
        "timestamp_second": 486.756,
        "relative_time": 9.014,
        "index": 161
    },
    {
        "type": "click",
        "e": "click",
        "timestamp": "2024-10-19T01:45:47.319Z",
        "target": "TEXTAREA",
        "x": 293,
        "y": 537,
        "timestamp_second": 487.032,
        "relative_time": 9.019111111111112,
        "index": 162
    },
    {
        "type": "mouseMovement",
        "totalMouseMovement": 112.33212376969095,
        "timestamp": "2024-10-19T01:45:47.320Z",
        "duration": 0.138,
        "timestamp_second": 487.033,
        "relative_time": 9.01912962962963,
        "index": 163
    },
    {
        "type": "paste",
        "timestamp": "2024-10-19T01:45:47.473Z",
        "text": "The official language is Danish, but English is widely spoken in Copenhagen. Even so, it's good to know a few basic phrases in Danish. For instance, \"hej\" means \"hello\", \"farvel\" is \"thank you\", and \"tak\" means \"goodbye\".",
        "textLength": 221,
        "timestamp_second": 487.186,
        "relative_time": 9.021962962962963,
        "index": 164
    },
    {
        "type": "mouseMovement",
        "totalMouseMovement": 259.7877455979251,
        "timestamp": "2024-10-19T01:45:47.479Z",
        "duration": 3.41,
        "timestamp_second": 487.192,
        "relative_time": 9.022074074074075,
        "index": 165
    },
    {
        "type": "click",
        "e": "click",
        "timestamp": "2024-10-19T01:45:51.072Z",
        "target": "TEXTAREA",
        "x": 323,
        "y": 637,
        "timestamp_second": 490.785,
        "relative_time": 9.088611111111112,
        "index": 166
    },
    {
        "type": "mouseMovement",
        "totalMouseMovement": 7.414213562373334,
        "timestamp": "2024-10-19T01:45:51.073Z",
        "duration": 0.174,
        "timestamp_second": 490.786,
        "relative_time": 9.08862962962963,
        "index": 167
    },
    {
        "type": "paste",
        "timestamp": "2024-10-19T01:45:51.254Z",
        "text": "The weather in Copenhagen in December is below -15 degrees Celsius. Make sure to dress warmly and appropriately for the weather.",
        "textLength": 128,
        "timestamp_second": 490.967,
        "relative_time": 9.091981481481481,
        "index": 168
    },
    {
        "type": "mouseMovement",
        "totalMouseMovement": 414.2659340623868,
        "timestamp": "2024-10-19T01:45:51.258Z",
        "duration": 0.224,
        "timestamp_second": 490.971,
        "relative_time": 9.092055555555556,
        "index": 169
    },
    {
        "type": "idle",
        "timestamp": "2024-10-19T01:45:54.482Z",
        "duration": 3.935,
        "timestamp_second": 494.195,
        "relative_time": 9.15175925925926,
        "index": 170
    },
    {
        "type": "mousewheel",
        "timestamp": "2024-10-19T01:45:55.417Z",
        "deltaY": 76,
        "yDirection": 1,
        "duration": 0.22,
        "timestamp_second": 495.13,
        "relative_time": 9.169074074074073,
        "index": 171
    },
    {
        "type": "scroll",
        "timestamp": "2024-10-19T01:45:56.139Z",
        "deltaY": 1,
        "yDirection": 1,
        "timestamp_second": 495.852,
        "relative_time": 9.182444444444444,
        "index": 172
    },
    {
        "type": "mouseMovement",
        "totalMouseMovement": 23.779271744369908,
        "timestamp": "2024-10-19T01:45:56.478Z",
        "duration": 0.205,
        "timestamp_second": 496.191,
        "relative_time": 9.188722222222221,
        "index": 173
    },
    {
        "type": "click",
        "e": "click",
        "timestamp": "2024-10-19T01:45:56.822Z",
        "target": "TEXTAREA",
        "x": 288,
        "y": 734,
        "timestamp_second": 496.535,
        "relative_time": 9.195092592592594,
        "index": 174
    },
    {
        "type": "mouseMovement",
        "totalMouseMovement": 41.09821669707526,
        "timestamp": "2024-10-19T01:45:56.823Z",
        "duration": 0.167,
        "timestamp_second": 496.536,
        "relative_time": 9.19511111111111,
        "index": 175
    },
    {
        "type": "paste",
        "timestamp": "2024-10-19T01:45:56.992Z",
        "text": "When booking a hotel in Copenhagen, it's best to do so well in advance, especially during peak tourist season. Many hotels offer discounts for early booking, so it's worth checking out. Also, consider the location of your hotel. Staying near a metro station can make your travel within the city much easier.",
        "textLength": 307,
        "timestamp_second": 496.705,
        "relative_time": 9.19824074074074,
        "index": 176
    },
    {
        "type": "mouseMovement",
        "totalMouseMovement": 415.1096592699214,
        "timestamp": "2024-10-19T01:45:56.999Z",
        "duration": 0.17,
        "timestamp_second": 496.712,
        "relative_time": 9.198370370370371,
        "index": 177
    },
    {
        "type": "idle",
        "timestamp": "2024-10-19T01:46:00.170Z",
        "duration": 5.593999999999999,
        "timestamp_second": 499.883,
        "relative_time": 9.257092592592592,
        "index": 178
    },
    {
        "type": "mousewheel",
        "timestamp": "2024-10-19T01:46:02.763Z",
        "deltaY": 367,
        "yDirection": 1,
        "duration": 0.335,
        "timestamp_second": 502.476,
        "relative_time": 9.305111111111112,
        "index": 179
    },
    {
        "type": "scroll",
        "timestamp": "2024-10-19T01:46:03.599Z",
        "deltaY": 0,
        "yDirection": 0,
        "timestamp_second": 503.312,
        "relative_time": 9.320592592592593,
        "index": 180
    },
    {
        "type": "paste",
        "timestamp": "2024-10-19T01:46:03.706Z",
        "text": "Copenhagen follows left-hand drive. This is important to remember if you plan on driving during your visit.",
        "textLength": 107,
        "timestamp_second": 503.419,
        "relative_time": 9.322574074074073,
        "index": 181
    },
    {
        "type": "mouseMovement",
        "totalMouseMovement": 12.162277660168911,
        "timestamp": "2024-10-19T01:46:03.739Z",
        "duration": 1.012,
        "timestamp_second": 503.452,
        "relative_time": 9.323185185185185,
        "index": 182
    },
    {
        "type": "click",
        "e": "click",
        "timestamp": "2024-10-19T01:46:04.981Z",
        "target": "TEXTAREA",
        "x": 440,
        "y": 485,
        "timestamp_second": 504.694,
        "relative_time": 9.346185185185185,
        "index": 183
    },
    {
        "type": "mouseMovement",
        "totalMouseMovement": 586.6282654827992,
        "timestamp": "2024-10-19T01:46:05.234Z",
        "duration": 0.971,
        "timestamp_second": 504.947,
        "relative_time": 9.350870370370371,
        "index": 184
    }
]